{
"meta":{"test_sets":[],"test_metrics":[],"learn_metrics":[{"best_value":"Min","name":"RMSE"}],"launch_mode":"Train","parameters":"","iteration_count":1000,"learn_sets":["learn"],"name":"experiment"},
"iterations":[
{"learn":[6130080.926],"iteration":0,"passed_time":0.05081619738,"remaining_time":50.76538119},
{"learn":[5935207.054],"iteration":1,"passed_time":0.05507024292,"remaining_time":27.48005122},
{"learn":[5727360.887],"iteration":2,"passed_time":0.0590621822,"remaining_time":19.62833188},
{"learn":[5547409.746],"iteration":3,"passed_time":0.06318166332,"remaining_time":15.73223417},
{"learn":[5374555.237],"iteration":4,"passed_time":0.06735684583,"remaining_time":13.40401232},
{"learn":[5224620.751],"iteration":5,"passed_time":0.07148141296,"remaining_time":11.84208741},
{"learn":[5082710.603],"iteration":6,"passed_time":0.07550948947,"remaining_time":10.71156044},
{"learn":[4956189.615],"iteration":7,"passed_time":0.08096751699,"remaining_time":10.03997211},
{"learn":[4846123.749],"iteration":8,"passed_time":0.08480899435,"remaining_time":9.3384126},
{"learn":[4737908.027],"iteration":9,"passed_time":0.08884229519,"remaining_time":8.795387224},
{"learn":[4648870.544],"iteration":10,"passed_time":0.0928548521,"remaining_time":8.348495339},
{"learn":[4549653.166],"iteration":11,"passed_time":0.09692290492,"remaining_time":7.979985838},
{"learn":[4467106.756],"iteration":12,"passed_time":0.1008458354,"remaining_time":7.656526119},
{"learn":[4395598.948],"iteration":13,"passed_time":0.1048240954,"remaining_time":7.382611292},
{"learn":[4331777.105],"iteration":14,"passed_time":0.1088200943,"remaining_time":7.145852857},
{"learn":[4254611.165],"iteration":15,"passed_time":0.1128396948,"remaining_time":6.93964123},
{"learn":[4183605.833],"iteration":16,"passed_time":0.1171096719,"remaining_time":6.771694558},
{"learn":[4118702.987],"iteration":17,"passed_time":0.1212339514,"remaining_time":6.613985568},
{"learn":[4059968.123],"iteration":18,"passed_time":0.1257183282,"remaining_time":6.491035788},
{"learn":[4005416.887],"iteration":19,"passed_time":0.129833842,"remaining_time":6.361858257},
{"learn":[3964541.611],"iteration":20,"passed_time":0.1339970903,"remaining_time":6.246816735},
{"learn":[3924120.991],"iteration":21,"passed_time":0.1378547028,"remaining_time":6.12826815},
{"learn":[3890135.476],"iteration":22,"passed_time":0.1416048036,"remaining_time":6.015125787},
{"learn":[3858295],"iteration":23,"passed_time":0.1454250448,"remaining_time":5.913951824},
{"learn":[3827557.631],"iteration":24,"passed_time":0.1497709892,"remaining_time":5.841068577},
{"learn":[3800573.758],"iteration":25,"passed_time":0.1536358637,"remaining_time":5.755435818},
{"learn":[3773757.784],"iteration":26,"passed_time":0.158994611,"remaining_time":5.729694687},
{"learn":[3739650.559],"iteration":27,"passed_time":0.1632778324,"remaining_time":5.668073325},
{"learn":[3715102.966],"iteration":28,"passed_time":0.1671083118,"remaining_time":5.595247268},
{"learn":[3689408.22],"iteration":29,"passed_time":0.1709521087,"remaining_time":5.527451513},
{"learn":[3667904.293],"iteration":30,"passed_time":0.1746465231,"remaining_time":5.459112287},
{"learn":[3645991.73],"iteration":31,"passed_time":0.1784960846,"remaining_time":5.399506558},
{"learn":[3627082.367],"iteration":32,"passed_time":0.1823414491,"remaining_time":5.343157008},
{"learn":[3612064.912],"iteration":33,"passed_time":0.1862691308,"remaining_time":5.292234716},
{"learn":[3594629.411],"iteration":34,"passed_time":0.1908012322,"remaining_time":5.260662545},
{"learn":[3573371.764],"iteration":35,"passed_time":0.19492354,"remaining_time":5.219619238},
{"learn":[3555565.714],"iteration":36,"passed_time":0.1987320606,"remaining_time":5.172404713},
{"learn":[3536886.022],"iteration":37,"passed_time":0.2026157265,"remaining_time":5.129377076},
{"learn":[3521802.687],"iteration":38,"passed_time":0.2065190498,"remaining_time":5.0888412},
{"learn":[3511259.656],"iteration":39,"passed_time":0.2103143823,"remaining_time":5.047545174},
{"learn":[3500668.525],"iteration":40,"passed_time":0.2142946751,"remaining_time":5.012404717},
{"learn":[3490326.786],"iteration":41,"passed_time":0.2181548566,"remaining_time":4.976008395},
{"learn":[3475577.079],"iteration":42,"passed_time":0.2221932835,"remaining_time":4.945092379},
{"learn":[3467727.376],"iteration":43,"passed_time":0.2262711364,"remaining_time":4.916254691},
{"learn":[3459595.942],"iteration":44,"passed_time":0.2300278819,"remaining_time":4.881702827},
{"learn":[3450199.595],"iteration":45,"passed_time":0.2337728967,"remaining_time":4.848246598},
{"learn":[3440511.565],"iteration":46,"passed_time":0.237588906,"remaining_time":4.817494201},
{"learn":[3428204.579],"iteration":47,"passed_time":0.2417371761,"remaining_time":4.794453992},
{"learn":[3421900.366],"iteration":48,"passed_time":0.245457218,"remaining_time":4.763873761},
{"learn":[3415408.978],"iteration":49,"passed_time":0.2500090239,"remaining_time":4.750171454},
{"learn":[3408234.04],"iteration":50,"passed_time":0.2538942625,"remaining_time":4.724424609},
{"learn":[3403024.014],"iteration":51,"passed_time":0.2575162792,"remaining_time":4.694719859},
{"learn":[3396458.04],"iteration":52,"passed_time":0.261780215,"remaining_time":4.677469125},
{"learn":[3390459.914],"iteration":53,"passed_time":0.2656269528,"remaining_time":4.653390692},
{"learn":[3384728.829],"iteration":54,"passed_time":0.2693403851,"remaining_time":4.627757526},
{"learn":[3377370.646],"iteration":55,"passed_time":0.2735236768,"remaining_time":4.610827694},
{"learn":[3368895.172],"iteration":56,"passed_time":0.2775629327,"remaining_time":4.591962202},
{"learn":[3364400.631],"iteration":57,"passed_time":0.2812113476,"remaining_time":4.567260163},
{"learn":[3357499.328],"iteration":58,"passed_time":0.2852601721,"remaining_time":4.549657999},
{"learn":[3352897.363],"iteration":59,"passed_time":0.2889733498,"remaining_time":4.527249147},
{"learn":[3344678.799],"iteration":60,"passed_time":0.2934893873,"remaining_time":4.517812044},
{"learn":[3340844.744],"iteration":61,"passed_time":0.2971727377,"remaining_time":4.495935935},
{"learn":[3335109.303],"iteration":62,"passed_time":0.3010029385,"remaining_time":4.476821482},
{"learn":[3330930.068],"iteration":63,"passed_time":0.3056428261,"remaining_time":4.470026332},
{"learn":[3327464.754],"iteration":64,"passed_time":0.3091762489,"remaining_time":4.447381426},
{"learn":[3322781.544],"iteration":65,"passed_time":0.3130205238,"remaining_time":4.429714685},
{"learn":[3315728.892],"iteration":66,"passed_time":0.3170971388,"remaining_time":4.415695978},
{"learn":[3311602.945],"iteration":67,"passed_time":0.3210043262,"remaining_time":4.399647529},
{"learn":[3308481.804],"iteration":68,"passed_time":0.3247817785,"remaining_time":4.382200519},
{"learn":[3305079.542],"iteration":69,"passed_time":0.3285241792,"remaining_time":4.364678381},
{"learn":[3299487.015],"iteration":70,"passed_time":0.3325032551,"remaining_time":4.350641183},
{"learn":[3296994.119],"iteration":71,"passed_time":0.3362670512,"remaining_time":4.33410866},
{"learn":[3294337.811],"iteration":72,"passed_time":0.3399592585,"remaining_time":4.317016885},
{"learn":[3291436.086],"iteration":73,"passed_time":0.3435618554,"remaining_time":4.29916592},
{"learn":[3286577.008],"iteration":74,"passed_time":0.3475459712,"remaining_time":4.286400312},
{"learn":[3281609.247],"iteration":75,"passed_time":0.3513605211,"remaining_time":4.27180423},
{"learn":[3279355.086],"iteration":76,"passed_time":0.3549269386,"remaining_time":4.254513822},
{"learn":[3276514.425],"iteration":77,"passed_time":0.3585406136,"remaining_time":4.23813392},
{"learn":[3273555.875],"iteration":78,"passed_time":0.362261261,"remaining_time":4.223324321},
{"learn":[3269899.244],"iteration":79,"passed_time":0.3660960475,"remaining_time":4.210104547},
{"learn":[3267476.5],"iteration":80,"passed_time":0.3700294036,"remaining_time":4.198234839},
{"learn":[3264011.368],"iteration":81,"passed_time":0.3740273481,"remaining_time":4.187281775},
{"learn":[3256768.255],"iteration":82,"passed_time":0.3778222055,"remaining_time":4.174252559},
{"learn":[3253124.556],"iteration":83,"passed_time":0.3818411655,"remaining_time":4.163886995},
{"learn":[3248527.263],"iteration":84,"passed_time":0.3858455311,"remaining_time":4.153513658},
{"learn":[3245909.735],"iteration":85,"passed_time":0.3894730447,"remaining_time":4.139283289},
{"learn":[3244358.474],"iteration":86,"passed_time":0.3931157592,"remaining_time":4.125456186},
{"learn":[3241703.373],"iteration":87,"passed_time":0.3968813416,"remaining_time":4.113133904},
{"learn":[3236999.261],"iteration":88,"passed_time":0.4010070584,"remaining_time":4.104690227},
{"learn":[3234721.335],"iteration":89,"passed_time":0.4050955685,"remaining_time":4.095966304},
{"learn":[3228798.266],"iteration":90,"passed_time":0.4091187044,"remaining_time":4.086691234},
{"learn":[3226700.366],"iteration":91,"passed_time":0.4127728037,"remaining_time":4.073888106},
{"learn":[3223172.196],"iteration":92,"passed_time":0.4167624285,"remaining_time":4.064554007},
{"learn":[3221292.32],"iteration":93,"passed_time":0.420605209,"remaining_time":4.053918291},
{"learn":[3218577.556],"iteration":94,"passed_time":0.4245149915,"remaining_time":4.044063866},
{"learn":[3216308.653],"iteration":95,"passed_time":0.4282926894,"remaining_time":4.033089492},
{"learn":[3214586.523],"iteration":96,"passed_time":0.4319322675,"remaining_time":4.020977707},
{"learn":[3212388.833],"iteration":97,"passed_time":0.435897581,"remaining_time":4.012036919},
{"learn":[3210028.6],"iteration":98,"passed_time":0.4397845386,"remaining_time":4.002483528},
{"learn":[3207999.61],"iteration":99,"passed_time":0.443744292,"remaining_time":3.993698628},
{"learn":[3203562.276],"iteration":100,"passed_time":0.4489864282,"remaining_time":3.996423752},
{"learn":[3200848.743],"iteration":101,"passed_time":0.4530696298,"remaining_time":3.988789486},
{"learn":[3197954.584],"iteration":102,"passed_time":0.4573209399,"remaining_time":3.982688185},
{"learn":[3195712.969],"iteration":103,"passed_time":0.4615938689,"remaining_time":3.976808717},
{"learn":[3194104.841],"iteration":104,"passed_time":0.4652521542,"remaining_time":3.965720743},
{"learn":[3191678.019],"iteration":105,"passed_time":0.4691610616,"remaining_time":3.956886689},
{"learn":[3189621.452],"iteration":106,"passed_time":0.4732832882,"remaining_time":3.949925013},
{"learn":[3187135.313],"iteration":107,"passed_time":0.4772940128,"remaining_time":3.942094995},
{"learn":[3185259.057],"iteration":108,"passed_time":0.4811760218,"remaining_time":3.933282893},
{"learn":[3184200.254],"iteration":109,"passed_time":0.4857208993,"remaining_time":3.92992364},
{"learn":[3182826.96],"iteration":110,"passed_time":0.489456938,"remaining_time":3.920065026},
{"learn":[3180780.141],"iteration":111,"passed_time":0.4931795199,"remaining_time":3.91020905},
{"learn":[3179295.517],"iteration":112,"passed_time":0.4974997646,"remaining_time":3.905153019},
{"learn":[3177152.384],"iteration":113,"passed_time":0.5011274115,"remaining_time":3.894727076},
{"learn":[3174402.906],"iteration":114,"passed_time":0.5049205539,"remaining_time":3.885692958},
{"learn":[3172548.052],"iteration":115,"passed_time":0.5087329457,"remaining_time":3.876895896},
{"learn":[3165950.224],"iteration":116,"passed_time":0.512895751,"remaining_time":3.870828616},
{"learn":[3164446.468],"iteration":117,"passed_time":0.5166530167,"remaining_time":3.861762379},
{"learn":[3162365.306],"iteration":118,"passed_time":0.5203569205,"remaining_time":3.852390311},
{"learn":[3160802.121],"iteration":119,"passed_time":0.5241841082,"remaining_time":3.844016793},
{"learn":[3158957.855],"iteration":120,"passed_time":0.5282989414,"remaining_time":3.837808012},
{"learn":[3158018.907],"iteration":121,"passed_time":0.5319851615,"remaining_time":3.828548949},
{"learn":[3156375.622],"iteration":122,"passed_time":0.5360803343,"remaining_time":3.822296367},
{"learn":[3152431.058],"iteration":123,"passed_time":0.5400800549,"remaining_time":3.815404259},
{"learn":[3150180.002],"iteration":124,"passed_time":0.5441349076,"remaining_time":3.808944353},
{"learn":[3148711.643],"iteration":125,"passed_time":0.5479428749,"remaining_time":3.800810101},
{"learn":[3147782.976],"iteration":126,"passed_time":0.551684603,"remaining_time":3.792288649},
{"learn":[3146375.933],"iteration":127,"passed_time":0.5556677706,"remaining_time":3.785486687},
{"learn":[3145552.746],"iteration":128,"passed_time":0.559842068,"remaining_time":3.780018924},
{"learn":[3143623.662],"iteration":129,"passed_time":0.5646451416,"remaining_time":3.778779024},
{"learn":[3142277],"iteration":130,"passed_time":0.5683293991,"remaining_time":3.77006296},
{"learn":[3139715.542],"iteration":131,"passed_time":0.5721823505,"remaining_time":3.762532426},
{"learn":[3137771.477],"iteration":132,"passed_time":0.5761771736,"remaining_time":3.755982026},
{"learn":[3136012.903],"iteration":133,"passed_time":0.5800563659,"remaining_time":3.748722484},
{"learn":[3134491.655],"iteration":134,"passed_time":0.5837795683,"remaining_time":3.74051353},
{"learn":[3131535.909],"iteration":135,"passed_time":0.5877396615,"remaining_time":3.733875496},
{"learn":[3130252.648],"iteration":136,"passed_time":0.5917099767,"remaining_time":3.727340948},
{"learn":[3129035.522],"iteration":137,"passed_time":0.5966090588,"remaining_time":3.72664499},
{"learn":[3127601.637],"iteration":138,"passed_time":0.6007666177,"remaining_time":3.72129538},
{"learn":[3126260.724],"iteration":139,"passed_time":0.6047249337,"remaining_time":3.714738878},
{"learn":[3125208.695],"iteration":140,"passed_time":0.6085304282,"remaining_time":3.707288211},
{"learn":[3124196.642],"iteration":141,"passed_time":0.6123932699,"remaining_time":3.700235392},
{"learn":[3122994.303],"iteration":142,"passed_time":0.6170705729,"remaining_time":3.698108258},
{"learn":[3121380.247],"iteration":143,"passed_time":0.6207660358,"remaining_time":3.690109213},
{"learn":[3119982.166],"iteration":144,"passed_time":0.624449748,"remaining_time":3.682100238},
{"learn":[3118838.257],"iteration":145,"passed_time":0.6283422387,"remaining_time":3.675371725},
{"learn":[3117275.196],"iteration":146,"passed_time":0.6325936501,"remaining_time":3.670764514},
{"learn":[3115769.522],"iteration":147,"passed_time":0.6362165027,"remaining_time":3.662543651},
{"learn":[3111691.249],"iteration":148,"passed_time":0.6401197107,"remaining_time":3.65598573},
{"learn":[3109950.204],"iteration":149,"passed_time":0.6447623649,"remaining_time":3.653653401},
{"learn":[3109160.537],"iteration":150,"passed_time":0.6483688279,"remaining_time":3.645464469},
{"learn":[3108162.278],"iteration":151,"passed_time":0.6518533603,"remaining_time":3.636655589},
{"learn":[3106903.26],"iteration":152,"passed_time":0.6559415105,"remaining_time":3.631257905},
{"learn":[3105733.895],"iteration":153,"passed_time":0.6597434937,"remaining_time":3.624305167},
{"learn":[3104444.608],"iteration":154,"passed_time":0.6634366171,"remaining_time":3.616799622},
{"learn":[3101381.234],"iteration":155,"passed_time":0.6679083782,"remaining_time":3.613555585},
{"learn":[3099964.352],"iteration":156,"passed_time":0.6723581073,"remaining_time":3.610177608},
{"learn":[3097732.823],"iteration":157,"passed_time":0.6764003884,"remaining_time":3.604614728},
{"learn":[3096910.509],"iteration":158,"passed_time":0.6802223437,"remaining_time":3.597905604},
{"learn":[3094559.486],"iteration":159,"passed_time":0.6841565849,"remaining_time":3.59182207},
{"learn":[3093484.741],"iteration":160,"passed_time":0.6878742381,"remaining_time":3.584636558},
{"learn":[3092757.652],"iteration":161,"passed_time":0.6913391182,"remaining_time":3.576186303},
{"learn":[3091496.923],"iteration":162,"passed_time":0.6949554585,"remaining_time":3.568574962},
{"learn":[3090123.06],"iteration":163,"passed_time":0.6987708212,"remaining_time":3.562026869},
{"learn":[3088493.914],"iteration":164,"passed_time":0.7026097797,"remaining_time":3.555631309},
{"learn":[3086581.179],"iteration":165,"passed_time":0.7067214223,"remaining_time":3.550636543},
{"learn":[3085255.571],"iteration":166,"passed_time":0.7106718005,"remaining_time":3.544847963},
{"learn":[3083900.793],"iteration":167,"passed_time":0.7150209514,"remaining_time":3.54105614},
{"learn":[3082686.024],"iteration":168,"passed_time":0.7186880294,"remaining_time":3.533903861},
{"learn":[3082022.017],"iteration":169,"passed_time":0.7221845661,"remaining_time":3.52595994},
{"learn":[3077929.034],"iteration":170,"passed_time":0.7261836302,"remaining_time":3.520504266},
{"learn":[3076069.232],"iteration":171,"passed_time":0.7301417236,"remaining_time":3.514868297},
{"learn":[3074664.622],"iteration":172,"passed_time":0.7340097917,"remaining_time":3.508821374},
{"learn":[3072406.25],"iteration":173,"passed_time":0.7379077062,"remaining_time":3.50294118},
{"learn":[3071518.106],"iteration":174,"passed_time":0.741722215,"remaining_time":3.496690442},
{"learn":[3070164.018],"iteration":175,"passed_time":0.7457289922,"remaining_time":3.491367555},
{"learn":[3068454.126],"iteration":176,"passed_time":0.7494198573,"remaining_time":3.484590636},
{"learn":[3067168.3],"iteration":177,"passed_time":0.7533281463,"remaining_time":3.478852451},
{"learn":[3066029.936],"iteration":178,"passed_time":0.7568481002,"remaining_time":3.471353577},
{"learn":[3064874.541],"iteration":179,"passed_time":0.7605365135,"remaining_time":3.464666339},
{"learn":[3060844.184],"iteration":180,"passed_time":0.7645557803,"remaining_time":3.459509304},
{"learn":[3060032.773],"iteration":181,"passed_time":0.7681845349,"remaining_time":3.452609613},
{"learn":[3058680.247],"iteration":182,"passed_time":0.7718534883,"remaining_time":3.445925136},
{"learn":[3057601.987],"iteration":183,"passed_time":0.775486532,"remaining_time":3.439114185},
{"learn":[3056391.756],"iteration":184,"passed_time":0.7791391338,"remaining_time":3.432423752},
{"learn":[3054295.617],"iteration":185,"passed_time":0.7833066803,"remaining_time":3.428019558},
{"learn":[3053026.612],"iteration":186,"passed_time":0.7872218776,"remaining_time":3.422520783},
{"learn":[3051285.364],"iteration":187,"passed_time":0.7913131762,"remaining_time":3.417799463},
{"learn":[3049581.333],"iteration":188,"passed_time":0.7954088903,"remaining_time":3.413103757},
{"learn":[3048062.184],"iteration":189,"passed_time":0.7991709583,"remaining_time":3.40699198},
{"learn":[3047084.494],"iteration":190,"passed_time":0.8029381555,"remaining_time":3.400926533},
{"learn":[3045445.384],"iteration":191,"passed_time":0.806873374,"remaining_time":3.395592115},
{"learn":[3044641.733],"iteration":192,"passed_time":0.8106154027,"remaining_time":3.389464404},
{"learn":[3042210.446],"iteration":193,"passed_time":0.8148402554,"remaining_time":3.385367247},
{"learn":[3040971.9],"iteration":194,"passed_time":0.8186124153,"remaining_time":3.379399971},
{"learn":[3039728.432],"iteration":195,"passed_time":0.8225423754,"remaining_time":3.374102397},
{"learn":[3038571.283],"iteration":196,"passed_time":0.8262795016,"remaining_time":3.368032689},
{"learn":[3037374.623],"iteration":197,"passed_time":0.8301410142,"remaining_time":3.362490371},
{"learn":[3034844.045],"iteration":198,"passed_time":0.8342233377,"remaining_time":3.357853736},
{"learn":[3033697.87],"iteration":199,"passed_time":0.8377395728,"remaining_time":3.350958291},
{"learn":[3032383.156],"iteration":200,"passed_time":0.8421435851,"remaining_time":3.347625495},
{"learn":[3031769.029],"iteration":201,"passed_time":0.8455499592,"remaining_time":3.340340928},
{"learn":[3030608.006],"iteration":202,"passed_time":0.8492522783,"remaining_time":3.334256482},
{"learn":[3028305.543],"iteration":203,"passed_time":0.8536585549,"remaining_time":3.330942204},
{"learn":[3027125.911],"iteration":204,"passed_time":0.8641037693,"remaining_time":3.351036569},
{"learn":[3026102.494],"iteration":205,"passed_time":0.8693796351,"remaining_time":3.350909856},
{"learn":[3025075.777],"iteration":206,"passed_time":0.8732207747,"remaining_time":3.345237074},
{"learn":[3023627.611],"iteration":207,"passed_time":0.8769968949,"remaining_time":3.339334331},
{"learn":[3022335.668],"iteration":208,"passed_time":0.8808318649,"remaining_time":3.333674666},
{"learn":[3021348.625],"iteration":209,"passed_time":0.8853770823,"remaining_time":3.330704262},
{"learn":[3020227.009],"iteration":210,"passed_time":0.8897072524,"remaining_time":3.326914797},
{"learn":[3019205.613],"iteration":211,"passed_time":0.8934041908,"remaining_time":3.32076652},
{"learn":[3017605.621],"iteration":212,"passed_time":0.8970677254,"remaining_time":3.31451784},
{"learn":[3014192.623],"iteration":213,"passed_time":0.9012918023,"remaining_time":3.310352134},
{"learn":[3011720.727],"iteration":214,"passed_time":0.9053319914,"remaining_time":3.30551448},
{"learn":[3010609.49],"iteration":215,"passed_time":0.909127399,"remaining_time":3.299795745},
{"learn":[3009708.152],"iteration":216,"passed_time":0.9137388005,"remaining_time":3.297039082},
{"learn":[3008240.838],"iteration":217,"passed_time":0.9176301605,"remaining_time":3.291682503},
{"learn":[3007411.45],"iteration":218,"passed_time":0.9214023956,"remaining_time":3.285914479},
{"learn":[3006512.216],"iteration":219,"passed_time":0.9249572599,"remaining_time":3.279393921},
{"learn":[3005718.335],"iteration":220,"passed_time":0.9286842472,"remaining_time":3.273506917},
{"learn":[3004848.181],"iteration":221,"passed_time":0.9323615162,"remaining_time":3.267465133},
{"learn":[3003881.592],"iteration":222,"passed_time":0.9359486366,"remaining_time":3.261130451},
{"learn":[3001596.612],"iteration":223,"passed_time":0.9400443326,"remaining_time":3.256582152},
{"learn":[3000410.333],"iteration":224,"passed_time":0.9439133469,"remaining_time":3.251257084},
{"learn":[2999544.333],"iteration":225,"passed_time":0.9475738484,"remaining_time":3.24523079},
{"learn":[2998642.476],"iteration":226,"passed_time":0.951268752,"remaining_time":3.23934249},
{"learn":[2997588.864],"iteration":227,"passed_time":0.9553657701,"remaining_time":3.234834976},
{"learn":[2996485.541],"iteration":228,"passed_time":0.958909847,"remaining_time":3.228469398},
{"learn":[2995817.98],"iteration":229,"passed_time":0.9623903359,"remaining_time":3.221915472},
{"learn":[2995179.955],"iteration":230,"passed_time":0.9660436283,"remaining_time":3.215963421},
{"learn":[2994442.623],"iteration":231,"passed_time":0.9695425867,"remaining_time":3.209520287},
{"learn":[2992041.11],"iteration":232,"passed_time":0.973604912,"remaining_time":3.204956942},
{"learn":[2990775.485],"iteration":233,"passed_time":0.9774052594,"remaining_time":3.199540294},
{"learn":[2990003.572],"iteration":234,"passed_time":0.9807815685,"remaining_time":3.192757021},
{"learn":[2988081.827],"iteration":235,"passed_time":0.9845351806,"remaining_time":3.187224059},
{"learn":[2986780.153],"iteration":236,"passed_time":0.9883197337,"remaining_time":3.181805725},
{"learn":[2985661.927],"iteration":237,"passed_time":0.9924487373,"remaining_time":3.17750394},
{"learn":[2984321.964],"iteration":238,"passed_time":0.996479447,"remaining_time":3.172890624},
{"learn":[2982915.621],"iteration":239,"passed_time":1.000494475,"remaining_time":3.168232503},
{"learn":[2981918.104],"iteration":240,"passed_time":1.004076582,"remaining_time":3.16221629},
{"learn":[2981123.414],"iteration":241,"passed_time":1.007900897,"remaining_time":3.156978843},
{"learn":[2980553.028],"iteration":242,"passed_time":1.011562285,"remaining_time":3.151245471},
{"learn":[2979573.615],"iteration":243,"passed_time":1.015489305,"remaining_time":3.146352109},
{"learn":[2978592.131],"iteration":244,"passed_time":1.019342978,"remaining_time":3.141240606},
{"learn":[2977952.739],"iteration":245,"passed_time":1.023071224,"remaining_time":3.135754891},
{"learn":[2977234.978],"iteration":246,"passed_time":1.026950647,"remaining_time":3.130744281},
{"learn":[2976140.897],"iteration":247,"passed_time":1.030783403,"remaining_time":3.125601286},
{"learn":[2975469.217],"iteration":248,"passed_time":1.034538761,"remaining_time":3.12023538},
{"learn":[2974258.961],"iteration":249,"passed_time":1.039717414,"remaining_time":3.119152241},
{"learn":[2973526.458],"iteration":250,"passed_time":1.043614727,"remaining_time":3.11421287},
{"learn":[2972102.625],"iteration":251,"passed_time":1.047620171,"remaining_time":3.109602729},
{"learn":[2970839.566],"iteration":252,"passed_time":1.052036038,"remaining_time":3.106209172},
{"learn":[2970053.615],"iteration":253,"passed_time":1.055785032,"remaining_time":3.100848953},
{"learn":[2969204.098],"iteration":254,"passed_time":1.059237444,"remaining_time":3.094634885},
{"learn":[2967343.821],"iteration":255,"passed_time":1.063058428,"remaining_time":3.089513556},
{"learn":[2966220.277],"iteration":256,"passed_time":1.066866804,"remaining_time":3.084365897},
{"learn":[2964991.421],"iteration":257,"passed_time":1.070918422,"remaining_time":3.079928176},
{"learn":[2963835.174],"iteration":258,"passed_time":1.074698641,"remaining_time":3.074716962},
{"learn":[2962616.199],"iteration":259,"passed_time":1.078610783,"remaining_time":3.069892229},
{"learn":[2961947.789],"iteration":260,"passed_time":1.082704287,"remaining_time":3.065588001},
{"learn":[2961154.715],"iteration":261,"passed_time":1.086265893,"remaining_time":3.059787135},
{"learn":[2960099.708],"iteration":262,"passed_time":1.091549578,"remaining_time":3.058829044},
{"learn":[2959000.082],"iteration":263,"passed_time":1.095256825,"remaining_time":3.053443271},
{"learn":[2958208.314],"iteration":264,"passed_time":1.098759679,"remaining_time":3.04750326},
{"learn":[2957056.25],"iteration":265,"passed_time":1.102959863,"remaining_time":3.043505788},
{"learn":[2956559.006],"iteration":266,"passed_time":1.106497391,"remaining_time":3.037687593},
{"learn":[2955494.142],"iteration":267,"passed_time":1.110525721,"remaining_time":3.033226969},
{"learn":[2954751.231],"iteration":268,"passed_time":1.114336394,"remaining_time":3.028178081},
{"learn":[2953877.24],"iteration":269,"passed_time":1.118857877,"remaining_time":3.025060186},
{"learn":[2953029.644],"iteration":270,"passed_time":1.122577865,"remaining_time":3.01977588},
{"learn":[2952234.938],"iteration":271,"passed_time":1.126176529,"remaining_time":3.014178358},
{"learn":[2951161.02],"iteration":272,"passed_time":1.130211158,"remaining_time":3.009756455},
{"learn":[2950475.292],"iteration":273,"passed_time":1.133913379,"remaining_time":3.004456618},
{"learn":[2949549.787],"iteration":274,"passed_time":1.137869641,"remaining_time":2.999838145},
{"learn":[2948423.576],"iteration":275,"passed_time":1.141723344,"remaining_time":2.994955437},
{"learn":[2947300.988],"iteration":276,"passed_time":1.145876537,"remaining_time":2.990861864},
{"learn":[2946769.285],"iteration":277,"passed_time":1.150633835,"remaining_time":2.988336794},
{"learn":[2945268.708],"iteration":278,"passed_time":1.154526763,"remaining_time":2.983561992},
{"learn":[2944164.358],"iteration":279,"passed_time":1.158170247,"remaining_time":2.978152063},
{"learn":[2943439.89],"iteration":280,"passed_time":1.161704575,"remaining_time":2.972475407},
{"learn":[2942290.938],"iteration":281,"passed_time":1.165566709,"remaining_time":2.967648571},
{"learn":[2941007.837],"iteration":282,"passed_time":1.16959037,"remaining_time":2.963237792},
{"learn":[2940405.938],"iteration":283,"passed_time":1.173175216,"remaining_time":2.957723432},
{"learn":[2939473.211],"iteration":284,"passed_time":1.177118109,"remaining_time":2.953120869},
{"learn":[2937785.431],"iteration":285,"passed_time":1.181259319,"remaining_time":2.94901802},
{"learn":[2936889.535],"iteration":286,"passed_time":1.185634458,"remaining_time":2.945496058},
{"learn":[2935739.496],"iteration":287,"passed_time":1.189607422,"remaining_time":2.940973903},
{"learn":[2933715.662],"iteration":288,"passed_time":1.193606154,"remaining_time":2.936518946},
{"learn":[2932674.348],"iteration":289,"passed_time":1.197241826,"remaining_time":2.931178263},
{"learn":[2931752.153],"iteration":290,"passed_time":1.202663568,"remaining_time":2.930200926},
{"learn":[2930417.759],"iteration":291,"passed_time":1.208421832,"remaining_time":2.930009101},
{"learn":[2929351.519],"iteration":292,"passed_time":1.213572981,"remaining_time":2.928314326},
{"learn":[2928509.186],"iteration":293,"passed_time":1.217155041,"remaining_time":2.922828091},
{"learn":[2927705.936],"iteration":294,"passed_time":1.220886746,"remaining_time":2.917712393},
{"learn":[2927024.643],"iteration":295,"passed_time":1.224478424,"remaining_time":2.912273009},
{"learn":[2926193.311],"iteration":296,"passed_time":1.227920428,"remaining_time":2.906491788},
{"learn":[2925352.539],"iteration":297,"passed_time":1.231966668,"remaining_time":2.902149666},
{"learn":[2924471.156],"iteration":298,"passed_time":1.236946829,"remaining_time":2.899999087},
{"learn":[2922880.608],"iteration":299,"passed_time":1.241633844,"remaining_time":2.897145635},
{"learn":[2922186.71],"iteration":300,"passed_time":1.245603163,"remaining_time":2.892613324},
{"learn":[2921278.451],"iteration":301,"passed_time":1.2497342,"remaining_time":2.888458515},
{"learn":[2920419.795],"iteration":302,"passed_time":1.253315484,"remaining_time":2.883039248},
{"learn":[2919131.378],"iteration":303,"passed_time":1.257220964,"remaining_time":2.878374312},
{"learn":[2918153.924],"iteration":304,"passed_time":1.261225512,"remaining_time":2.873940101},
{"learn":[2917522.161],"iteration":305,"passed_time":1.264879502,"remaining_time":2.868713642},
{"learn":[2917227.862],"iteration":306,"passed_time":1.268491147,"remaining_time":2.863401841},
{"learn":[2916156.4],"iteration":307,"passed_time":1.272343692,"remaining_time":2.85864232},
{"learn":[2915071.543],"iteration":308,"passed_time":1.275911155,"remaining_time":2.853251158},
{"learn":[2914199.651],"iteration":309,"passed_time":1.279336303,"remaining_time":2.847554997},
{"learn":[2913361.536],"iteration":310,"passed_time":1.283147662,"remaining_time":2.842729066},
{"learn":[2912563.248],"iteration":311,"passed_time":1.286931764,"remaining_time":2.837849532},
{"learn":[2912206.633],"iteration":312,"passed_time":1.290835274,"remaining_time":2.833239084},
{"learn":[2911778.628],"iteration":313,"passed_time":1.294464757,"remaining_time":2.82803447},
{"learn":[2910732.145],"iteration":314,"passed_time":1.29852928,"remaining_time":2.823785894},
{"learn":[2909996.426],"iteration":315,"passed_time":1.303575542,"remaining_time":2.821663515},
{"learn":[2908632.047],"iteration":316,"passed_time":1.307564684,"remaining_time":2.817245044},
{"learn":[2908094.897],"iteration":317,"passed_time":1.311098483,"remaining_time":2.811852722},
{"learn":[2907366.58],"iteration":318,"passed_time":1.314461595,"remaining_time":2.806107669},
{"learn":[2907056.41],"iteration":319,"passed_time":1.317798658,"remaining_time":2.800322148},
{"learn":[2906117.294],"iteration":320,"passed_time":1.321497581,"remaining_time":2.795317313},
{"learn":[2905798.026],"iteration":321,"passed_time":1.325191844,"remaining_time":2.790310777},
{"learn":[2904835.028],"iteration":322,"passed_time":1.329182423,"remaining_time":2.785933438},
{"learn":[2904487.33],"iteration":323,"passed_time":1.332714591,"remaining_time":2.780602048},
{"learn":[2903668.984],"iteration":324,"passed_time":1.336438797,"remaining_time":2.775680578},
{"learn":[2902041.05],"iteration":325,"passed_time":1.34108215,"remaining_time":2.772666775},
{"learn":[2901575.417],"iteration":326,"passed_time":1.344626572,"remaining_time":2.767381294},
{"learn":[2900421.062],"iteration":327,"passed_time":1.348405809,"remaining_time":2.762587511},
{"learn":[2899225.134],"iteration":328,"passed_time":1.352013231,"remaining_time":2.757449477},
{"learn":[2898116.003],"iteration":329,"passed_time":1.355884032,"remaining_time":2.752855458},
{"learn":[2897299.695],"iteration":330,"passed_time":1.35958064,"remaining_time":2.747913741},
{"learn":[2896815.747],"iteration":331,"passed_time":1.363029846,"remaining_time":2.742481739},
{"learn":[2895842.142],"iteration":332,"passed_time":1.366757515,"remaining_time":2.737619407},
{"learn":[2894275.573],"iteration":333,"passed_time":1.370589257,"remaining_time":2.732971392},
{"learn":[2893424.023],"iteration":334,"passed_time":1.374472028,"remaining_time":2.728429549},
{"learn":[2892215.418],"iteration":335,"passed_time":1.378262184,"remaining_time":2.723708601},
{"learn":[2891761.897],"iteration":336,"passed_time":1.382589109,"remaining_time":2.720049197},
{"learn":[2891215.241],"iteration":337,"passed_time":1.386623286,"remaining_time":2.715812471},
{"learn":[2890291.179],"iteration":338,"passed_time":1.390535234,"remaining_time":2.711338612},
{"learn":[2888937.598],"iteration":339,"passed_time":1.395119297,"remaining_time":2.708172752},
{"learn":[2888563.25],"iteration":340,"passed_time":1.39925913,"remaining_time":2.704140078},
{"learn":[2887473.805],"iteration":341,"passed_time":1.403296004,"remaining_time":2.699908686},
{"learn":[2887020.918],"iteration":342,"passed_time":1.406873166,"remaining_time":2.694797872},
{"learn":[2886070.091],"iteration":343,"passed_time":1.410733598,"remaining_time":2.690236164},
{"learn":[2885552.649],"iteration":344,"passed_time":1.41456152,"remaining_time":2.6856168},
{"learn":[2884067.099],"iteration":345,"passed_time":1.418813966,"remaining_time":2.681804433},
{"learn":[2883368.246],"iteration":346,"passed_time":1.42251871,"remaining_time":2.67695884},
{"learn":[2882505.502],"iteration":347,"passed_time":1.426461291,"remaining_time":2.672565407},
{"learn":[2881119.817],"iteration":348,"passed_time":1.430576939,"remaining_time":2.668497385},
{"learn":[2880180.062],"iteration":349,"passed_time":1.435447851,"remaining_time":2.665831724},
{"learn":[2879696.599],"iteration":350,"passed_time":1.439397026,"remaining_time":2.661449202},
{"learn":[2879027.262],"iteration":351,"passed_time":1.443105388,"remaining_time":2.656625828},
{"learn":[2878111.183],"iteration":352,"passed_time":1.447774337,"remaining_time":2.653569395},
{"learn":[2877683.782],"iteration":353,"passed_time":1.451219005,"remaining_time":2.648269709},
{"learn":[2876520.016],"iteration":354,"passed_time":1.454787833,"remaining_time":2.643206063},
{"learn":[2876419.274],"iteration":355,"passed_time":1.458261033,"remaining_time":2.637977823},
{"learn":[2875493.152],"iteration":356,"passed_time":1.462164738,"remaining_time":2.633534808},
{"learn":[2874797.967],"iteration":357,"passed_time":1.465782759,"remaining_time":2.62858249},
{"learn":[2873911.212],"iteration":358,"passed_time":1.469754871,"remaining_time":2.624269839},
{"learn":[2872349.759],"iteration":359,"passed_time":1.473681569,"remaining_time":2.619878345},
{"learn":[2871587.604],"iteration":360,"passed_time":1.477517408,"remaining_time":2.615328598},
{"learn":[2870894.025],"iteration":361,"passed_time":1.481518066,"remaining_time":2.611073276},
{"learn":[2870168.56],"iteration":362,"passed_time":1.486896286,"remaining_time":2.609236734},
{"learn":[2869332.708],"iteration":363,"passed_time":1.49068242,"remaining_time":2.604598954},
{"learn":[2868250.659],"iteration":364,"passed_time":1.494411049,"remaining_time":2.599865798},
{"learn":[2867302.007],"iteration":365,"passed_time":1.498396502,"remaining_time":2.595583012},
{"learn":[2866286.523],"iteration":366,"passed_time":1.502132939,"remaining_time":2.590872344},
{"learn":[2865534.812],"iteration":367,"passed_time":1.505972157,"remaining_time":2.586343487},
{"learn":[2864854.76],"iteration":368,"passed_time":1.509627438,"remaining_time":2.58150383},
{"learn":[2864137.905],"iteration":369,"passed_time":1.513592218,"remaining_time":2.577197561},
{"learn":[2863185.24],"iteration":370,"passed_time":1.517690417,"remaining_time":2.573119332},
{"learn":[2862826.239],"iteration":371,"passed_time":1.521516081,"remaining_time":2.568580911},
{"learn":[2862095.159],"iteration":372,"passed_time":1.52524796,"remaining_time":2.563888662},
{"learn":[2861020.731],"iteration":373,"passed_time":1.529139187,"remaining_time":2.559468264},
{"learn":[2860054.535],"iteration":374,"passed_time":1.533202335,"remaining_time":2.555337225},
{"learn":[2859720.573],"iteration":375,"passed_time":1.536747475,"remaining_time":2.550346874},
{"learn":[2858833.122],"iteration":376,"passed_time":1.540691549,"remaining_time":2.546023435},
{"learn":[2858300.798],"iteration":377,"passed_time":1.544351786,"remaining_time":2.541234949},
{"learn":[2857537.512],"iteration":378,"passed_time":1.548036735,"remaining_time":2.536492908},
{"learn":[2857344.056],"iteration":379,"passed_time":1.551491685,"remaining_time":2.531381171},
{"learn":[2856632.071],"iteration":380,"passed_time":1.555372216,"remaining_time":2.526969558},
{"learn":[2854789.068],"iteration":381,"passed_time":1.559478917,"remaining_time":2.522926624},
{"learn":[2854412.353],"iteration":382,"passed_time":1.562941439,"remaining_time":2.517845608},
{"learn":[2853463.123],"iteration":383,"passed_time":1.566707137,"remaining_time":2.513259365},
{"learn":[2852943.178],"iteration":384,"passed_time":1.570338441,"remaining_time":2.508462705},
{"learn":[2852826.432],"iteration":385,"passed_time":1.573695894,"remaining_time":2.503236474},
{"learn":[2852186.655],"iteration":386,"passed_time":1.577530999,"remaining_time":2.498776493},
{"learn":[2851011.705],"iteration":387,"passed_time":1.581518486,"remaining_time":2.494560086},
{"learn":[2850083.156],"iteration":388,"passed_time":1.585598375,"remaining_time":2.490489992},
{"learn":[2849608.621],"iteration":389,"passed_time":1.589212595,"remaining_time":2.485691495},
{"learn":[2848858.242],"iteration":390,"passed_time":1.593133576,"remaining_time":2.481376849},
{"learn":[2848283.546],"iteration":391,"passed_time":1.597789978,"remaining_time":2.478204863},
{"learn":[2848212.43],"iteration":392,"passed_time":1.601183273,"remaining_time":2.473074419},
{"learn":[2847645.406],"iteration":393,"passed_time":1.605163489,"remaining_time":2.468855518},
{"learn":[2846699.315],"iteration":394,"passed_time":1.608835944,"remaining_time":2.464166446},
{"learn":[2846212.817],"iteration":395,"passed_time":1.612637807,"remaining_time":2.459679888},
{"learn":[2845760.089],"iteration":396,"passed_time":1.616279385,"remaining_time":2.454953323},
{"learn":[2845125.965],"iteration":397,"passed_time":1.620087698,"remaining_time":2.450484408},
{"learn":[2844101.126],"iteration":398,"passed_time":1.624072746,"remaining_time":2.446285014},
{"learn":[2843004.706],"iteration":399,"passed_time":1.629105805,"remaining_time":2.443658708},
{"learn":[2841938.11],"iteration":400,"passed_time":1.634967349,"remaining_time":2.44225796},
{"learn":[2841325.426],"iteration":401,"passed_time":1.639057738,"remaining_time":2.438200317},
{"learn":[2840509.541],"iteration":402,"passed_time":1.643029329,"remaining_time":2.433966525},
{"learn":[2839541.939],"iteration":403,"passed_time":1.6471938,"remaining_time":2.430018576},
{"learn":[2838664.489],"iteration":404,"passed_time":1.651162851,"remaining_time":2.42578246},
{"learn":[2837722.68],"iteration":405,"passed_time":1.655208299,"remaining_time":2.421659433},
{"learn":[2837190.302],"iteration":406,"passed_time":1.658764198,"remaining_time":2.416823512},
{"learn":[2836414.711],"iteration":407,"passed_time":1.66258723,"remaining_time":2.412381471},
{"learn":[2835462.932],"iteration":408,"passed_time":1.6664642,"remaining_time":2.408020397},
{"learn":[2835004.681],"iteration":409,"passed_time":1.670223605,"remaining_time":2.403492504},
{"learn":[2833700.327],"iteration":410,"passed_time":1.674248278,"remaining_time":2.399348506},
{"learn":[2832819.887],"iteration":411,"passed_time":1.678262699,"remaining_time":2.395190453},
{"learn":[2832628.349],"iteration":412,"passed_time":1.681943454,"remaining_time":2.390558856},
{"learn":[2831960.159],"iteration":413,"passed_time":1.685726412,"remaining_time":2.386076516},
{"learn":[2831026.984],"iteration":414,"passed_time":1.689565119,"remaining_time":2.381676132},
{"learn":[2830353.046],"iteration":415,"passed_time":1.69327178,"remaining_time":2.377093076},
{"learn":[2829451.507],"iteration":416,"passed_time":1.697008552,"remaining_time":2.372556321},
{"learn":[2829190.402],"iteration":417,"passed_time":1.700396552,"remaining_time":2.367537784},
{"learn":[2828385.796],"iteration":418,"passed_time":1.705292215,"remaining_time":2.364617607},
{"learn":[2827724.304],"iteration":419,"passed_time":1.709373715,"remaining_time":2.360563702},
{"learn":[2826616.608],"iteration":420,"passed_time":1.713419392,"remaining_time":2.356460399},
{"learn":[2826138.83],"iteration":421,"passed_time":1.71693503,"remaining_time":2.351631391},
{"learn":[2825694.298],"iteration":422,"passed_time":1.720779071,"remaining_time":2.347256558},
{"learn":[2824998.611],"iteration":423,"passed_time":1.724373187,"remaining_time":2.342544707},
{"learn":[2824879.265],"iteration":424,"passed_time":1.72798189,"remaining_time":2.337857852},
{"learn":[2823930.376],"iteration":425,"passed_time":1.731814874,"remaining_time":2.333478257},
{"learn":[2822754.985],"iteration":426,"passed_time":1.735645575,"remaining_time":2.32909816},
{"learn":[2821951.114],"iteration":427,"passed_time":1.74025292,"remaining_time":2.325758575},
{"learn":[2821515.123],"iteration":428,"passed_time":1.74385635,"remaining_time":2.321076867},
{"learn":[2820629.31],"iteration":429,"passed_time":1.747949073,"remaining_time":2.317048772},
{"learn":[2819752.386],"iteration":430,"passed_time":1.751950307,"remaining_time":2.312899593},
{"learn":[2819286.808],"iteration":431,"passed_time":1.75588193,"remaining_time":2.308659574},
{"learn":[2819252.4],"iteration":432,"passed_time":1.759383488,"remaining_time":2.303857824},
{"learn":[2818672.639],"iteration":433,"passed_time":1.762863743,"remaining_time":2.299034283},
{"learn":[2817746.175],"iteration":434,"passed_time":1.76688298,"remaining_time":2.294916974},
{"learn":[2816978.454],"iteration":435,"passed_time":1.770956549,"remaining_time":2.290870398},
{"learn":[2816311.515],"iteration":436,"passed_time":1.77456161,"remaining_time":2.286220106},
{"learn":[2815084.418],"iteration":437,"passed_time":1.778431229,"remaining_time":2.281914043},
{"learn":[2814204.924],"iteration":438,"passed_time":1.782431915,"remaining_time":2.277777459},
{"learn":[2814063.461],"iteration":439,"passed_time":1.785975407,"remaining_time":2.273059609},
{"learn":[2813417.021],"iteration":440,"passed_time":1.789836578,"remaining_time":2.268749766},
{"learn":[2812642.988],"iteration":441,"passed_time":1.793634626,"remaining_time":2.264362266},
{"learn":[2811678.923],"iteration":442,"passed_time":1.797654549,"remaining_time":2.260256397},
{"learn":[2811616.289],"iteration":443,"passed_time":1.801371124,"remaining_time":2.255771048},
{"learn":[2810773.506],"iteration":444,"passed_time":1.805107376,"remaining_time":2.251313693},
{"learn":[2809542.699],"iteration":445,"passed_time":1.809343567,"remaining_time":2.247480574},
{"learn":[2808344.359],"iteration":446,"passed_time":1.813089971,"remaining_time":2.243039718},
{"learn":[2807639.063],"iteration":447,"passed_time":1.816855106,"remaining_time":2.238625042},
{"learn":[2807096.973],"iteration":448,"passed_time":1.820652886,"remaining_time":2.234253319},
{"learn":[2806280.796],"iteration":449,"passed_time":1.824415082,"remaining_time":2.229840656},
{"learn":[2805576.612],"iteration":450,"passed_time":1.828523314,"remaining_time":2.225852105},
{"learn":[2805467.51],"iteration":451,"passed_time":1.834025505,"remaining_time":2.223553046},
{"learn":[2804625.903],"iteration":452,"passed_time":1.837904427,"remaining_time":2.219279739},
{"learn":[2804013.146],"iteration":453,"passed_time":1.841777543,"remaining_time":2.215001186},
{"learn":[2803337.112],"iteration":454,"passed_time":1.845634093,"remaining_time":2.210704573},
{"learn":[2802215.026],"iteration":455,"passed_time":1.849315626,"remaining_time":2.206201098},
{"learn":[2800507.613],"iteration":456,"passed_time":1.853196992,"remaining_time":2.201938657},
{"learn":[2800346.097],"iteration":457,"passed_time":1.856399105,"remaining_time":2.19687405},
{"learn":[2799595.625],"iteration":458,"passed_time":1.860015147,"remaining_time":2.192305435},
{"learn":[2797920.61],"iteration":459,"passed_time":1.864060846,"remaining_time":2.188245341},
{"learn":[2796990.698],"iteration":460,"passed_time":1.867683562,"remaining_time":2.183690759},
{"learn":[2795844.83],"iteration":461,"passed_time":1.871675952,"remaining_time":2.179570697},
{"learn":[2794157.688],"iteration":462,"passed_time":1.876142619,"remaining_time":2.176001267},
{"learn":[2793901.754],"iteration":463,"passed_time":1.880698007,"remaining_time":2.172530456},
{"learn":[2793703.888],"iteration":464,"passed_time":1.8844858,"remaining_time":2.168171835},
{"learn":[2792936.393],"iteration":465,"passed_time":1.888183112,"remaining_time":2.163711978},
{"learn":[2792130.379],"iteration":466,"passed_time":1.891740403,"remaining_time":2.159095577},
{"learn":[2792108.27],"iteration":467,"passed_time":1.894807383,"remaining_time":2.153926341},
{"learn":[2791441.782],"iteration":468,"passed_time":1.898278351,"remaining_time":2.149223464},
{"learn":[2790847.056],"iteration":469,"passed_time":1.901854248,"remaining_time":2.144644152},
{"learn":[2790331.204],"iteration":470,"passed_time":1.905504716,"remaining_time":2.140152855},
{"learn":[2789650.435],"iteration":471,"passed_time":1.909176971,"remaining_time":2.135689493},
{"learn":[2788976.463],"iteration":472,"passed_time":1.913152548,"remaining_time":2.131567427},
{"learn":[2788242.866],"iteration":473,"passed_time":1.917177109,"remaining_time":2.127500336},
{"learn":[2787870.308],"iteration":474,"passed_time":1.920939438,"remaining_time":2.123143589},
{"learn":[2787128.765],"iteration":475,"passed_time":1.924767722,"remaining_time":2.118861946},
{"learn":[2786672.317],"iteration":476,"passed_time":1.928463522,"remaining_time":2.114436943},
{"learn":[2786127.972],"iteration":477,"passed_time":1.932095006,"remaining_time":2.109944755},
{"learn":[2785842.719],"iteration":478,"passed_time":1.935623717,"remaining_time":2.105344376},
{"learn":[2785763.171],"iteration":479,"passed_time":1.939042577,"remaining_time":2.100629458},
{"learn":[2785210.136],"iteration":480,"passed_time":1.942683555,"remaining_time":2.096159595},
{"learn":[2784973.495],"iteration":481,"passed_time":1.94614854,"remaining_time":2.091504032},
{"learn":[2784268.874],"iteration":482,"passed_time":1.950032006,"remaining_time":2.08730134},
{"learn":[2783492.948],"iteration":483,"passed_time":1.953717715,"remaining_time":2.082889134},
{"learn":[2782613.596],"iteration":484,"passed_time":1.957385549,"remaining_time":2.078460944},
{"learn":[2781582.477],"iteration":485,"passed_time":1.961568309,"remaining_time":2.074580475},
{"learn":[2780434.216],"iteration":486,"passed_time":1.965935231,"remaining_time":2.070892759},
{"learn":[2779761.055],"iteration":487,"passed_time":1.969630681,"remaining_time":2.066497764},
{"learn":[2778373.09],"iteration":488,"passed_time":1.973813739,"remaining_time":2.062615175},
{"learn":[2778353.909],"iteration":489,"passed_time":1.977011037,"remaining_time":2.057705365},
{"learn":[2777955.476],"iteration":490,"passed_time":1.980741077,"remaining_time":2.053354803},
{"learn":[2777456.759],"iteration":491,"passed_time":1.98473551,"remaining_time":2.049279754},
{"learn":[2777178.166],"iteration":492,"passed_time":1.988348091,"remaining_time":2.044812337},
{"learn":[2776632.345],"iteration":493,"passed_time":1.992196555,"remaining_time":2.040589993},
{"learn":[2776143.117],"iteration":494,"passed_time":1.995954685,"remaining_time":2.036277001},
{"learn":[2775692.767],"iteration":495,"passed_time":1.999574728,"remaining_time":2.031825933},
{"learn":[2775168.095],"iteration":496,"passed_time":2.003638805,"remaining_time":2.027827603},
{"learn":[2774956.393],"iteration":497,"passed_time":2.007401842,"remaining_time":2.023525552},
{"learn":[2774187.296],"iteration":498,"passed_time":2.011364666,"remaining_time":2.019426248},
{"learn":[2773148.79],"iteration":499,"passed_time":2.015218315,"remaining_time":2.015218315},
{"learn":[2772097.821],"iteration":500,"passed_time":2.019135842,"remaining_time":2.011075419},
{"learn":[2771249.865],"iteration":501,"passed_time":2.023162007,"remaining_time":2.007041194},
{"learn":[2770432.799],"iteration":502,"passed_time":2.027317861,"remaining_time":2.003135143},
{"learn":[2769585.819],"iteration":503,"passed_time":2.03244857,"remaining_time":2.000187482},
{"learn":[2768796.345],"iteration":504,"passed_time":2.036244235,"remaining_time":1.995922567},
{"learn":[2768054.884],"iteration":505,"passed_time":2.04040559,"remaining_time":1.992016525},
{"learn":[2767626.242],"iteration":506,"passed_time":2.044395634,"remaining_time":1.987942895},
{"learn":[2767176.766],"iteration":507,"passed_time":2.048088934,"remaining_time":1.983582196},
{"learn":[2766293.109],"iteration":508,"passed_time":2.052194468,"remaining_time":1.979621776},
{"learn":[2765562.033],"iteration":509,"passed_time":2.056422581,"remaining_time":1.975778558},
{"learn":[2764825.422],"iteration":510,"passed_time":2.060455429,"remaining_time":1.971746976},
{"learn":[2764427.257],"iteration":511,"passed_time":2.064310914,"remaining_time":1.96754634},
{"learn":[2763961.82],"iteration":512,"passed_time":2.068210303,"remaining_time":1.963388728},
{"learn":[2763579.016],"iteration":513,"passed_time":2.071987688,"remaining_time":1.959116763},
{"learn":[2763336.558],"iteration":514,"passed_time":2.076045382,"remaining_time":1.9551107},
{"learn":[2762730.617],"iteration":515,"passed_time":2.081070467,"remaining_time":1.952011833},
{"learn":[2762211.629],"iteration":516,"passed_time":2.086593642,"remaining_time":1.949370849},
{"learn":[2761882.803],"iteration":517,"passed_time":2.090168267,"remaining_time":1.944905607},
{"learn":[2761632.557],"iteration":518,"passed_time":2.093737046,"remaining_time":1.94043838},
{"learn":[2761023.842],"iteration":519,"passed_time":2.097520787,"remaining_time":1.936173034},
{"learn":[2760326.062],"iteration":520,"passed_time":2.101213184,"remaining_time":1.931825557},
{"learn":[2760152.936],"iteration":521,"passed_time":2.104769345,"remaining_time":1.927355837},
{"learn":[2759584.261],"iteration":522,"passed_time":2.108546518,"remaining_time":1.923091183},
{"learn":[2758612.314],"iteration":523,"passed_time":2.113042566,"remaining_time":1.919481415},
{"learn":[2757442.095],"iteration":524,"passed_time":2.116822932,"remaining_time":1.915220748},
{"learn":[2757063.649],"iteration":525,"passed_time":2.120388138,"remaining_time":1.910768018},
{"learn":[2755934.73],"iteration":526,"passed_time":2.124224574,"remaining_time":1.906562094},
{"learn":[2755331.633],"iteration":527,"passed_time":2.127860735,"remaining_time":1.902178536},
{"learn":[2754686.696],"iteration":528,"passed_time":2.131706568,"remaining_time":1.897984487},
{"learn":[2753251.981],"iteration":529,"passed_time":2.135742017,"remaining_time":1.893959902},
{"learn":[2751999.388],"iteration":530,"passed_time":2.139578843,"remaining_time":1.889759845},
{"learn":[2751230.202],"iteration":531,"passed_time":2.143427244,"remaining_time":1.885571335},
{"learn":[2750139.887],"iteration":532,"passed_time":2.148465291,"remaining_time":1.882426437},
{"learn":[2749165.038],"iteration":533,"passed_time":2.152437137,"remaining_time":1.878344018},
{"learn":[2748716.823],"iteration":534,"passed_time":2.156448639,"remaining_time":1.874296481},
{"learn":[2748237.651],"iteration":535,"passed_time":2.160111549,"remaining_time":1.869947311},
{"learn":[2747591.933],"iteration":536,"passed_time":2.164170115,"remaining_time":1.865941831},
{"learn":[2746956.476],"iteration":537,"passed_time":2.16798218,"remaining_time":1.861724474},
{"learn":[2746349.279],"iteration":538,"passed_time":2.172160386,"remaining_time":1.857821777},
{"learn":[2746011.715],"iteration":539,"passed_time":2.175813388,"remaining_time":1.853470664},
{"learn":[2745271.759],"iteration":540,"passed_time":2.179878133,"remaining_time":1.849471466},
{"learn":[2743943.771],"iteration":541,"passed_time":2.184386677,"remaining_time":1.845847045},
{"learn":[2743298.948],"iteration":542,"passed_time":2.188044541,"remaining_time":1.841503417},
{"learn":[2742668.984],"iteration":543,"passed_time":2.191636778,"remaining_time":1.837107299},
{"learn":[2742228.662],"iteration":544,"passed_time":2.195264834,"remaining_time":1.832744036},
{"learn":[2741047.221],"iteration":545,"passed_time":2.199091516,"remaining_time":1.828548623},
{"learn":[2740910.072],"iteration":546,"passed_time":2.202813997,"remaining_time":1.824268264},
{"learn":[2740123.366],"iteration":547,"passed_time":2.206666495,"remaining_time":1.820097182},
{"learn":[2739945.37],"iteration":548,"passed_time":2.210225542,"remaining_time":1.815686192},
{"learn":[2739262.522],"iteration":549,"passed_time":2.214204248,"remaining_time":1.811621657},
{"learn":[2738746.066],"iteration":550,"passed_time":2.217959042,"remaining_time":1.807374973},
{"learn":[2737943.594],"iteration":551,"passed_time":2.222206032,"remaining_time":1.803529533},
{"learn":[2737420.566],"iteration":552,"passed_time":2.225861246,"remaining_time":1.799204299},
{"learn":[2736577.28],"iteration":553,"passed_time":2.230940283,"remaining_time":1.796027737},
{"learn":[2735870.182],"iteration":554,"passed_time":2.234995817,"remaining_time":1.792023673},
{"learn":[2735186.537],"iteration":555,"passed_time":2.238807947,"remaining_time":1.787825051},
{"learn":[2734581.786],"iteration":556,"passed_time":2.243145413,"remaining_time":1.784045633},
{"learn":[2733813.508],"iteration":557,"passed_time":2.246860595,"remaining_time":1.779771296},
{"learn":[2732967.1],"iteration":558,"passed_time":2.250601666,"remaining_time":1.775519382},
{"learn":[2732691.434],"iteration":559,"passed_time":2.254275276,"remaining_time":1.771216288},
{"learn":[2732101.258],"iteration":560,"passed_time":2.258141883,"remaining_time":1.767066464},
{"learn":[2731102.673],"iteration":561,"passed_time":2.262158618,"remaining_time":1.763034653},
{"learn":[2730776.183],"iteration":562,"passed_time":2.265845851,"remaining_time":1.758747135},
{"learn":[2730210.275],"iteration":563,"passed_time":2.269750575,"remaining_time":1.754629877},
{"learn":[2729806.786],"iteration":564,"passed_time":2.273477591,"remaining_time":1.750376552},
{"learn":[2729126.159],"iteration":565,"passed_time":2.277264376,"remaining_time":1.746170917},
{"learn":[2728767.183],"iteration":566,"passed_time":2.282094919,"remaining_time":1.742763844},
{"learn":[2728275.581],"iteration":567,"passed_time":2.285661129,"remaining_time":1.738390154},
{"learn":[2727237.935],"iteration":568,"passed_time":2.289645461,"remaining_time":1.734336017},
{"learn":[2726593.921],"iteration":569,"passed_time":2.293251194,"remaining_time":1.729996515},
{"learn":[2726287.644],"iteration":570,"passed_time":2.2968863,"remaining_time":1.725681651},
{"learn":[2725822.746],"iteration":571,"passed_time":2.300598468,"remaining_time":1.721426826},
{"learn":[2725474.602],"iteration":572,"passed_time":2.304062295,"remaining_time":1.71698883},
{"learn":[2724991.25],"iteration":573,"passed_time":2.307845451,"remaining_time":1.712791224},
{"learn":[2724513.224],"iteration":574,"passed_time":2.311717204,"remaining_time":1.708660542},
{"learn":[2723895.116],"iteration":575,"passed_time":2.315715615,"remaining_time":1.704623994},
{"learn":[2723407.258],"iteration":576,"passed_time":2.31917584,"remaining_time":1.700193033},
{"learn":[2722891.725],"iteration":577,"passed_time":2.322982295,"remaining_time":1.696018215},
{"learn":[2722651.319],"iteration":578,"passed_time":2.326646858,"remaining_time":1.691741498},
{"learn":[2722376.137],"iteration":579,"passed_time":2.330455302,"remaining_time":1.687571081},
{"learn":[2721904.892],"iteration":580,"passed_time":2.334178052,"remaining_time":1.68334011},
{"learn":[2721042.238],"iteration":581,"passed_time":2.33768153,"remaining_time":1.678953402},
{"learn":[2720754.322],"iteration":582,"passed_time":2.34111787,"remaining_time":1.674521701},
{"learn":[2719898.911],"iteration":583,"passed_time":2.344865704,"remaining_time":1.670315296},
{"learn":[2719244.817],"iteration":584,"passed_time":2.348598755,"remaining_time":1.666099972},
{"learn":[2718694.82],"iteration":585,"passed_time":2.352288229,"remaining_time":1.661855507},
{"learn":[2718345.397],"iteration":586,"passed_time":2.355857067,"remaining_time":1.657528056},
{"learn":[2718117.204],"iteration":587,"passed_time":2.359413466,"remaining_time":1.65319447},
{"learn":[2717536.799],"iteration":588,"passed_time":2.363398619,"remaining_time":1.649162703},
{"learn":[2716947.714],"iteration":589,"passed_time":2.367489668,"remaining_time":1.645204684},
{"learn":[2716333.273],"iteration":590,"passed_time":2.371439063,"remaining_time":1.641148184},
{"learn":[2716071.951],"iteration":591,"passed_time":2.375390299,"remaining_time":1.637093314},
{"learn":[2715585.211],"iteration":592,"passed_time":2.379388538,"remaining_time":1.633071054},
{"learn":[2715322.478],"iteration":593,"passed_time":2.382968558,"remaining_time":1.628763021},
{"learn":[2714566.116],"iteration":594,"passed_time":2.386949631,"remaining_time":1.624730421},
{"learn":[2713785.435],"iteration":595,"passed_time":2.39065661,"remaining_time":1.620512199},
{"learn":[2713163.222],"iteration":596,"passed_time":2.396266078,"remaining_time":1.617579949},
{"learn":[2712499.614],"iteration":597,"passed_time":2.400418732,"remaining_time":1.613659415},
{"learn":[2711621.223],"iteration":598,"passed_time":2.404128425,"remaining_time":1.609441567},
{"learn":[2710887.488],"iteration":599,"passed_time":2.407881788,"remaining_time":1.605254526},
{"learn":[2710114.028],"iteration":600,"passed_time":2.411762593,"remaining_time":1.601153535},
{"learn":[2708973.024],"iteration":601,"passed_time":2.415634835,"remaining_time":1.597047615},
{"learn":[2708540.304],"iteration":602,"passed_time":2.419450846,"remaining_time":1.592905449},
{"learn":[2707784.662],"iteration":603,"passed_time":2.423357464,"remaining_time":1.588823768},
{"learn":[2707415.986],"iteration":604,"passed_time":2.427326743,"remaining_time":1.584783576},
{"learn":[2707359.643],"iteration":605,"passed_time":2.430915147,"remaining_time":1.580495987},
{"learn":[2706643.646],"iteration":606,"passed_time":2.434995655,"remaining_time":1.576529312},
{"learn":[2706084.779],"iteration":607,"passed_time":2.439508848,"remaining_time":1.572841231},
{"learn":[2705274.299],"iteration":608,"passed_time":2.443652595,"remaining_time":1.568913243},
{"learn":[2704726.639],"iteration":609,"passed_time":2.4474543,"remaining_time":1.564765864},
{"learn":[2704712.121],"iteration":610,"passed_time":2.450741479,"remaining_time":1.560292038},
{"learn":[2703962.37],"iteration":611,"passed_time":2.454751424,"remaining_time":1.556280314},
{"learn":[2703104.325],"iteration":612,"passed_time":2.459072216,"remaining_time":1.552464841},
{"learn":[2702717.956],"iteration":613,"passed_time":2.462959611,"remaining_time":1.54837526},
{"learn":[2702591.023],"iteration":614,"passed_time":2.466504527,"remaining_time":1.54407194},
{"learn":[2702198.16],"iteration":615,"passed_time":2.470353671,"remaining_time":1.53996073},
{"learn":[2701410.75],"iteration":616,"passed_time":2.474196893,"remaining_time":1.535846694},
{"learn":[2700621.701],"iteration":617,"passed_time":2.479454128,"remaining_time":1.532607568},
{"learn":[2700021.93],"iteration":618,"passed_time":2.483285192,"remaining_time":1.5284841},
{"learn":[2698743.756],"iteration":619,"passed_time":2.487401455,"remaining_time":1.524536376},
{"learn":[2697837.567],"iteration":620,"passed_time":2.491476261,"remaining_time":1.520562807},
{"learn":[2697692.161],"iteration":621,"passed_time":2.494925797,"remaining_time":1.516208925},
{"learn":[2696146.965],"iteration":622,"passed_time":2.49904071,"remaining_time":1.51226059},
{"learn":[2696080.547],"iteration":623,"passed_time":2.502561455,"remaining_time":1.507953697},
{"learn":[2696023.785],"iteration":624,"passed_time":2.505956683,"remaining_time":1.50357401},
{"learn":[2695447.152],"iteration":625,"passed_time":2.509711903,"remaining_time":1.499412542},
{"learn":[2694865.638],"iteration":626,"passed_time":2.513799935,"remaining_time":1.49545036},
{"learn":[2693923.748],"iteration":627,"passed_time":2.517882646,"remaining_time":1.491484625},
{"learn":[2693336.041],"iteration":628,"passed_time":2.521480483,"remaining_time":1.487232526},
{"learn":[2692398.601],"iteration":629,"passed_time":2.525367432,"remaining_time":1.483152301},
{"learn":[2692362.4],"iteration":630,"passed_time":2.528600764,"remaining_time":1.478690463},
{"learn":[2691746.219],"iteration":631,"passed_time":2.532302293,"remaining_time":1.474505133},
{"learn":[2691041.287],"iteration":632,"passed_time":2.536249099,"remaining_time":1.470463538},
{"learn":[2690065.701],"iteration":633,"passed_time":2.540436788,"remaining_time":1.4665613},
{"learn":[2689295.049],"iteration":634,"passed_time":2.544402313,"remaining_time":1.462530463},
{"learn":[2688543.239],"iteration":635,"passed_time":2.548154806,"remaining_time":1.458377908},
{"learn":[2687930.468],"iteration":636,"passed_time":2.552039075,"remaining_time":1.454301702},
{"learn":[2686787.985],"iteration":637,"passed_time":2.556238714,"remaining_time":1.450405038},
{"learn":[2685973.035],"iteration":638,"passed_time":2.560067081,"remaining_time":1.446297678},
{"learn":[2685502.633],"iteration":639,"passed_time":2.563691236,"remaining_time":1.44207632},
{"learn":[2685152.692],"iteration":640,"passed_time":2.567326886,"remaining_time":1.437863264},
{"learn":[2684498.283],"iteration":641,"passed_time":2.571468278,"remaining_time":1.433934024},
{"learn":[2683928.268],"iteration":642,"passed_time":2.576188924,"remaining_time":1.430325732},
{"learn":[2683681.479],"iteration":643,"passed_time":2.579624864,"remaining_time":1.426003807},
{"learn":[2683086.831],"iteration":644,"passed_time":2.583532354,"remaining_time":1.421944164},
{"learn":[2682590.921],"iteration":645,"passed_time":2.587081207,"remaining_time":1.417688463},
{"learn":[2682270.8],"iteration":646,"passed_time":2.590467326,"remaining_time":1.413346161},
{"learn":[2681644.871],"iteration":647,"passed_time":2.594231499,"remaining_time":1.409212172},
{"learn":[2681116.652],"iteration":648,"passed_time":2.597902769,"remaining_time":1.405029079},
{"learn":[2680754.482],"iteration":649,"passed_time":2.601665911,"remaining_time":1.400897029},
{"learn":[2680129.113],"iteration":650,"passed_time":2.60577584,"remaining_time":1.396952025},
{"learn":[2679624.757],"iteration":651,"passed_time":2.611136304,"remaining_time":1.393673978},
{"learn":[2679170.845],"iteration":652,"passed_time":2.614916989,"remaining_time":1.389550069},
{"learn":[2678640.678],"iteration":653,"passed_time":2.619274329,"remaining_time":1.38573229},
{"learn":[2678017.609],"iteration":654,"passed_time":2.623280401,"remaining_time":1.381727845},
{"learn":[2677911.333],"iteration":655,"passed_time":2.627576977,"remaining_time":1.377875732},
{"learn":[2677194.625],"iteration":656,"passed_time":2.631583574,"remaining_time":1.373870877},
{"learn":[2676803.826],"iteration":657,"passed_time":2.635386123,"remaining_time":1.36975996},
{"learn":[2676218.957],"iteration":658,"passed_time":2.639582921,"remaining_time":1.365853985},
{"learn":[2675655.691],"iteration":659,"passed_time":2.64362737,"remaining_time":1.361868645},
{"learn":[2674976.119],"iteration":660,"passed_time":2.647366129,"remaining_time":1.357726351},
{"learn":[2674563.229],"iteration":661,"passed_time":2.651375976,"remaining_time":1.353723686},
{"learn":[2674000.983],"iteration":662,"passed_time":2.654960641,"remaining_time":1.349504881},
{"learn":[2673335.864],"iteration":663,"passed_time":2.658726198,"remaining_time":1.345379522},
{"learn":[2672852.531],"iteration":664,"passed_time":2.662394357,"remaining_time":1.34120618},
{"learn":[2672729.312],"iteration":665,"passed_time":2.665964218,"remaining_time":1.336985058},
{"learn":[2672619.493],"iteration":666,"passed_time":2.669622326,"remaining_time":1.332809947},
{"learn":[2672594.308],"iteration":667,"passed_time":2.672931381,"remaining_time":1.328462902},
{"learn":[2671685.004],"iteration":668,"passed_time":2.67724612,"remaining_time":1.324616541},
{"learn":[2670835.068],"iteration":669,"passed_time":2.681258896,"remaining_time":1.320620053},
{"learn":[2670262.671],"iteration":670,"passed_time":2.685005331,"remaining_time":1.316492927},
{"learn":[2669918.569],"iteration":671,"passed_time":2.68982816,"remaining_time":1.312892316},
{"learn":[2669220.054],"iteration":672,"passed_time":2.693615824,"remaining_time":1.308785103},
{"learn":[2668566.055],"iteration":673,"passed_time":2.697623182,"remaining_time":1.3047851},
{"learn":[2668441.964],"iteration":674,"passed_time":2.701108051,"remaining_time":1.300533506},
{"learn":[2668042.782],"iteration":675,"passed_time":2.704817667,"remaining_time":1.2963919},
{"learn":[2667675.792],"iteration":676,"passed_time":2.708389781,"remaining_time":1.292185967},
{"learn":[2666998.716],"iteration":677,"passed_time":2.712043202,"remaining_time":1.288020518},
{"learn":[2666532.141],"iteration":678,"passed_time":2.715693385,"remaining_time":1.283855047},
{"learn":[2665913.462],"iteration":679,"passed_time":2.719649742,"remaining_time":1.279835173},
{"learn":[2665352.676],"iteration":680,"passed_time":2.72386852,"remaining_time":1.275938411},
{"learn":[2664873.756],"iteration":681,"passed_time":2.727498372,"remaining_time":1.271766103},
{"learn":[2664554.739],"iteration":682,"passed_time":2.731233761,"remaining_time":1.267644367},
{"learn":[2663968.123],"iteration":683,"passed_time":2.735029751,"remaining_time":1.263551756},
{"learn":[2663580.581],"iteration":684,"passed_time":2.738724885,"remaining_time":1.259413633},
{"learn":[2663557.586],"iteration":685,"passed_time":2.742102203,"remaining_time":1.255131329},
{"learn":[2663010.911],"iteration":686,"passed_time":2.745856406,"remaining_time":1.25102337},
{"learn":[2662858.387],"iteration":687,"passed_time":2.749803294,"remaining_time":1.247003819},
{"learn":[2662428.107],"iteration":688,"passed_time":2.753490599,"remaining_time":1.24286731},
{"learn":[2662378.349],"iteration":689,"passed_time":2.756868838,"remaining_time":1.238593246},
{"learn":[2661727.463],"iteration":690,"passed_time":2.760714384,"remaining_time":1.234530745},
{"learn":[2661439.405],"iteration":691,"passed_time":2.764451436,"remaining_time":1.230420581},
{"learn":[2660672.344],"iteration":692,"passed_time":2.768506845,"remaining_time":1.226452527},
{"learn":[2660242.53],"iteration":693,"passed_time":2.772182095,"remaining_time":1.222316601},
{"learn":[2659795.462],"iteration":694,"passed_time":2.776442194,"remaining_time":1.218438661},
{"learn":[2659350.668],"iteration":695,"passed_time":2.780159234,"remaining_time":1.214322424},
{"learn":[2658729.073],"iteration":696,"passed_time":2.784054096,"remaining_time":1.210284636},
{"learn":[2658132.143],"iteration":697,"passed_time":2.787869428,"remaining_time":1.206212847},
{"learn":[2657740.851],"iteration":698,"passed_time":2.791596809,"remaining_time":1.202103919},
{"learn":[2657158.594],"iteration":699,"passed_time":2.795617772,"remaining_time":1.198121902},
{"learn":[2656500.165],"iteration":700,"passed_time":2.799701941,"remaining_time":1.194166734},
{"learn":[2655516.052],"iteration":701,"passed_time":2.803815295,"remaining_time":1.190223587},
{"learn":[2655244.003],"iteration":702,"passed_time":2.807238183,"remaining_time":1.185988251},
{"learn":[2655160.262],"iteration":703,"passed_time":2.810508416,"remaining_time":1.181691039},
{"learn":[2655102.88],"iteration":704,"passed_time":2.813633524,"remaining_time":1.177336013},
{"learn":[2654366.557],"iteration":705,"passed_time":2.817522297,"remaining_time":1.173302486},
{"learn":[2653967.56],"iteration":706,"passed_time":2.821393883,"remaining_time":1.169262246},
{"learn":[2653489.128],"iteration":707,"passed_time":2.825812739,"remaining_time":1.165448192},
{"learn":[2653428.262],"iteration":708,"passed_time":2.829109238,"remaining_time":1.161171775},
{"learn":[2653407.125],"iteration":709,"passed_time":2.832228613,"remaining_time":1.156825772},
{"learn":[2652652.26],"iteration":710,"passed_time":2.836222771,"remaining_time":1.152838791},
{"learn":[2652038.002],"iteration":711,"passed_time":2.839994698,"remaining_time":1.1487619},
{"learn":[2651962.843],"iteration":712,"passed_time":2.843307347,"remaining_time":1.144500994},
{"learn":[2651412.392],"iteration":713,"passed_time":2.847046781,"remaining_time":1.140413696},
{"learn":[2650766.028],"iteration":714,"passed_time":2.850970439,"remaining_time":1.136400804},
{"learn":[2650328.742],"iteration":715,"passed_time":2.854843448,"remaining_time":1.132368071},
{"learn":[2649710.395],"iteration":716,"passed_time":2.858863427,"remaining_time":1.128393793},
{"learn":[2649280.986],"iteration":717,"passed_time":2.862744328,"remaining_time":1.124364764},
{"learn":[2648442.075],"iteration":718,"passed_time":2.8665997,"remaining_time":1.120326169},
{"learn":[2647857.759],"iteration":719,"passed_time":2.871883384,"remaining_time":1.116843538},
{"learn":[2647515.109],"iteration":720,"passed_time":2.87550783,"remaining_time":1.112713848},
{"learn":[2647137.019],"iteration":721,"passed_time":2.879073884,"remaining_time":1.108563074},
{"learn":[2646599.379],"iteration":722,"passed_time":2.882840377,"remaining_time":1.104490712},
{"learn":[2646075.721],"iteration":723,"passed_time":2.886653567,"remaining_time":1.100436995},
{"learn":[2645810.563],"iteration":724,"passed_time":2.890239636,"remaining_time":1.096297793},
{"learn":[2645757.869],"iteration":725,"passed_time":2.893776501,"remaining_time":1.092141544},
{"learn":[2645348.747],"iteration":726,"passed_time":2.89734588,"remaining_time":1.08799921},
{"learn":[2645339.942],"iteration":727,"passed_time":2.899907419,"remaining_time":1.083481893},
{"learn":[2645263.106],"iteration":728,"passed_time":2.903369418,"remaining_time":1.079304681},
{"learn":[2644370.269],"iteration":729,"passed_time":2.907485626,"remaining_time":1.075371396},
{"learn":[2643808.819],"iteration":730,"passed_time":2.911149844,"remaining_time":1.071271283},
{"learn":[2643570.332],"iteration":731,"passed_time":2.91483026,"remaining_time":1.067178292},
{"learn":[2643070.599],"iteration":732,"passed_time":2.918753121,"remaining_time":1.063174739},
{"learn":[2642521.373],"iteration":733,"passed_time":2.922388588,"remaining_time":1.059067254},
{"learn":[2642222.717],"iteration":734,"passed_time":2.926030036,"remaining_time":1.05496321},
{"learn":[2641675.178],"iteration":735,"passed_time":2.929520319,"remaining_time":1.050806201},
{"learn":[2641294.077],"iteration":736,"passed_time":2.933217162,"remaining_time":1.046724713},
{"learn":[2640809.642],"iteration":737,"passed_time":2.936801352,"remaining_time":1.042604274},
{"learn":[2640155.771],"iteration":738,"passed_time":2.940654061,"remaining_time":1.038580122},
{"learn":[2639605.524],"iteration":739,"passed_time":2.944772681,"remaining_time":1.034649861},
{"learn":[2638726.715],"iteration":740,"passed_time":2.949031147,"remaining_time":1.030767972},
{"learn":[2638502.536],"iteration":741,"passed_time":2.952844632,"remaining_time":1.026730344},
{"learn":[2638296.587],"iteration":742,"passed_time":2.956662948,"remaining_time":1.02269499},
{"learn":[2638159.406],"iteration":743,"passed_time":2.960132235,"remaining_time":1.018540124},
{"learn":[2637792.856],"iteration":744,"passed_time":2.96391653,"remaining_time":1.01449492},
{"learn":[2637247.678],"iteration":745,"passed_time":2.967511663,"remaining_time":1.010386009},
{"learn":[2636783.347],"iteration":746,"passed_time":2.971356829,"remaining_time":1.006363156},
{"learn":[2636551.244],"iteration":747,"passed_time":2.975042079,"remaining_time":1.002286904},
{"learn":[2636203.838],"iteration":748,"passed_time":2.978633257,"remaining_time":0.9981801702},
{"learn":[2635535.184],"iteration":749,"passed_time":2.982564885,"remaining_time":0.9941882949},
{"learn":[2635133.836],"iteration":750,"passed_time":2.986128268,"remaining_time":0.9900744857},
{"learn":[2634604.083],"iteration":751,"passed_time":2.989818894,"remaining_time":0.9860041032},
{"learn":[2633770.054],"iteration":752,"passed_time":2.99391689,"remaining_time":0.9820683557},
{"learn":[2633142.165],"iteration":753,"passed_time":2.998016323,"remaining_time":0.9781326465},
{"learn":[2632664.332],"iteration":754,"passed_time":3.001634374,"remaining_time":0.9740402936},
{"learn":[2632277.869],"iteration":755,"passed_time":3.005300745,"remaining_time":0.9699647906},
{"learn":[2631910.314],"iteration":756,"passed_time":3.00900355,"remaining_time":0.9659020642},
{"learn":[2631117.198],"iteration":757,"passed_time":3.012853158,"remaining_time":0.9618871561},
{"learn":[2630392.033],"iteration":758,"passed_time":3.018148641,"remaining_time":0.9583317818},
{"learn":[2630384.549],"iteration":759,"passed_time":3.020763745,"remaining_time":0.9539253932},
{"learn":[2629862.55],"iteration":760,"passed_time":3.025458308,"remaining_time":0.9501767878},
{"learn":[2629692.607],"iteration":761,"passed_time":3.028874513,"remaining_time":0.9460264227},
{"learn":[2629375.267],"iteration":762,"passed_time":3.032911756,"remaining_time":0.9420708862},
{"learn":[2629251.333],"iteration":763,"passed_time":3.036672866,"remaining_time":0.9380298382},
{"learn":[2628641.849],"iteration":764,"passed_time":3.04051186,"remaining_time":0.9340134473},
{"learn":[2627861.129],"iteration":765,"passed_time":3.044485164,"remaining_time":0.9300385487},
{"learn":[2627305.978],"iteration":766,"passed_time":3.048475808,"remaining_time":0.9260689221},
{"learn":[2627270.143],"iteration":767,"passed_time":3.051796153,"remaining_time":0.9218967546},
{"learn":[2626948.005],"iteration":768,"passed_time":3.055705345,"remaining_time":0.9179036862},
{"learn":[2626552.7],"iteration":769,"passed_time":3.059476785,"remaining_time":0.9138696891},
{"learn":[2626143.481],"iteration":770,"passed_time":3.063184812,"remaining_time":0.9098175381},
{"learn":[2625809.935],"iteration":771,"passed_time":3.068189943,"remaining_time":0.9061493614},
{"learn":[2624855.19],"iteration":772,"passed_time":3.072141775,"remaining_time":0.9021684125},
{"learn":[2624204.415],"iteration":773,"passed_time":3.076111388,"remaining_time":0.898192731},
{"learn":[2623715.334],"iteration":774,"passed_time":3.079745045,"remaining_time":0.8941195293},
{"learn":[2623264.772],"iteration":775,"passed_time":3.08356259,"remaining_time":0.8901005416},
{"learn":[2622895.594],"iteration":776,"passed_time":3.087487086,"remaining_time":0.8861127672},
{"learn":[2622412.849],"iteration":777,"passed_time":3.091509655,"remaining_time":0.8821531407},
{"learn":[2621512.479],"iteration":778,"passed_time":3.095677645,"remaining_time":0.8782346078},
{"learn":[2621137.778],"iteration":779,"passed_time":3.099441354,"remaining_time":0.8742014074},
{"learn":[2620664.499],"iteration":780,"passed_time":3.103203783,"remaining_time":0.8701685385},
{"learn":[2620657.501],"iteration":781,"passed_time":3.105756882,"remaining_time":0.865799233},
{"learn":[2620650.893],"iteration":782,"passed_time":3.108627612,"remaining_time":0.861522595},
{"learn":[2620395.914],"iteration":783,"passed_time":3.112426287,"remaining_time":0.8575052014},
{"learn":[2619860.465],"iteration":784,"passed_time":3.116384412,"remaining_time":0.8535320365},
{"learn":[2619605.651],"iteration":785,"passed_time":3.119923795,"remaining_time":0.8494449009},
{"learn":[2619011.441],"iteration":786,"passed_time":3.123651995,"remaining_time":0.8454102605},
{"learn":[2618934.35],"iteration":787,"passed_time":3.127003829,"remaining_time":0.8412751417},
{"learn":[2618094.713],"iteration":788,"passed_time":3.130659926,"remaining_time":0.8372233768},
{"learn":[2617504.154],"iteration":789,"passed_time":3.134241068,"remaining_time":0.8331526889},
{"learn":[2616940.132],"iteration":790,"passed_time":3.138199041,"remaining_time":0.8291828061},
{"learn":[2616723.188],"iteration":791,"passed_time":3.142068154,"remaining_time":0.8251896161},
{"learn":[2616659.838],"iteration":792,"passed_time":3.146555578,"remaining_time":0.8213581394},
{"learn":[2615844.521],"iteration":793,"passed_time":3.150510819,"remaining_time":0.817386938},
{"learn":[2615004.517],"iteration":794,"passed_time":3.154406013,"remaining_time":0.8134002928},
{"learn":[2614540.717],"iteration":795,"passed_time":3.158223357,"remaining_time":0.8093939256},
{"learn":[2613992.337],"iteration":796,"passed_time":3.162260972,"remaining_time":0.8054441371},
{"learn":[2613794.021],"iteration":797,"passed_time":3.165688119,"remaining_time":0.801339599},
{"learn":[2613449.654],"iteration":798,"passed_time":3.169517663,"remaining_time":0.7973379853},
{"learn":[2613045.167],"iteration":799,"passed_time":3.173039471,"remaining_time":0.7932598679},
{"learn":[2612898.691],"iteration":800,"passed_time":3.176446862,"remaining_time":0.7891547135},
{"learn":[2612497.256],"iteration":801,"passed_time":3.180140046,"remaining_time":0.7851218569},
{"learn":[2612148.839],"iteration":802,"passed_time":3.183651406,"remaining_time":0.7810452391},
{"learn":[2611436.062],"iteration":803,"passed_time":3.187654915,"remaining_time":0.7770900041},
{"learn":[2610875.063],"iteration":804,"passed_time":3.191416186,"remaining_time":0.7730759705},
{"learn":[2610621.973],"iteration":805,"passed_time":3.194958079,"remaining_time":0.7690097608},
{"learn":[2610120.612],"iteration":806,"passed_time":3.198943336,"remaining_time":0.7650508846},
{"learn":[2609532.081],"iteration":807,"passed_time":3.202832711,"remaining_time":0.7610691592},
{"learn":[2609238.939],"iteration":808,"passed_time":3.206515458,"remaining_time":0.7570388783},
{"learn":[2608775.864],"iteration":809,"passed_time":3.21048694,"remaining_time":0.7530771836},
{"learn":[2608283.038],"iteration":810,"passed_time":3.214491074,"remaining_time":0.7491230741},
{"learn":[2607716.666],"iteration":811,"passed_time":3.218317527,"remaining_time":0.7451277034},
{"learn":[2606951.692],"iteration":812,"passed_time":3.222795407,"remaining_time":0.7412825844},
{"learn":[2606652.873],"iteration":813,"passed_time":3.226382175,"remaining_time":0.7372322907},
{"learn":[2606161.671],"iteration":814,"passed_time":3.230094332,"remaining_time":0.7332115968},
{"learn":[2605790.107],"iteration":815,"passed_time":3.234655309,"remaining_time":0.7293830599},
{"learn":[2605009.484],"iteration":816,"passed_time":3.238918323,"remaining_time":0.7254859891},
{"learn":[2604625.477],"iteration":817,"passed_time":3.242762239,"remaining_time":0.7214947769},
{"learn":[2604150.911],"iteration":818,"passed_time":3.246972911,"remaining_time":0.717584978},
{"learn":[2603955.82],"iteration":819,"passed_time":3.250508275,"remaining_time":0.7135262066},
{"learn":[2603422.856],"iteration":820,"passed_time":3.254416144,"remaining_time":0.7095499266},
{"learn":[2602524.356],"iteration":821,"passed_time":3.258475447,"remaining_time":0.7056066053},
{"learn":[2602025.548],"iteration":822,"passed_time":3.262674409,"remaining_time":0.7016930382},
{"learn":[2601556.015],"iteration":823,"passed_time":3.266460978,"remaining_time":0.6976906944},
{"learn":[2601129.499],"iteration":824,"passed_time":3.270321472,"remaining_time":0.6937045548},
{"learn":[2600515.414],"iteration":825,"passed_time":3.275138121,"remaining_time":0.6899201369},
{"learn":[2600267.828],"iteration":826,"passed_time":3.278797917,"remaining_time":0.6858912208},
{"learn":[2600069.066],"iteration":827,"passed_time":3.282520724,"remaining_time":0.6818762857},
{"learn":[2599860.725],"iteration":828,"passed_time":3.286226487,"remaining_time":0.6778585394},
{"learn":[2599373.811],"iteration":829,"passed_time":3.290459935,"remaining_time":0.6739496253},
{"learn":[2598999.823],"iteration":830,"passed_time":3.29419751,"remaining_time":0.6699390844},
{"learn":[2598392.186],"iteration":831,"passed_time":3.298107079,"remaining_time":0.6659639294},
{"learn":[2596717.584],"iteration":832,"passed_time":3.302640699,"remaining_time":0.6621140416},
{"learn":[2596661.985],"iteration":833,"passed_time":3.305989502,"remaining_time":0.6580266874},
{"learn":[2596433.599],"iteration":834,"passed_time":3.309531258,"remaining_time":0.6539792307},
{"learn":[2595871.263],"iteration":835,"passed_time":3.313350007,"remaining_time":0.649987322},
{"learn":[2595330.635],"iteration":836,"passed_time":3.316794289,"remaining_time":0.6459229021},
{"learn":[2594929.315],"iteration":837,"passed_time":3.320473204,"remaining_time":0.6419053211},
{"learn":[2594622.144],"iteration":838,"passed_time":3.324090555,"remaining_time":0.6378767335},
{"learn":[2594102.173],"iteration":839,"passed_time":3.328204427,"remaining_time":0.6339437004},
{"learn":[2593537.705],"iteration":840,"passed_time":3.331985636,"remaining_time":0.6299473438},
{"learn":[2593204.525],"iteration":841,"passed_time":3.335464147,"remaining_time":0.6258946975},
{"learn":[2592185.292],"iteration":842,"passed_time":3.33971868,"remaining_time":0.6219879392},
{"learn":[2591568.54],"iteration":843,"passed_time":3.346856008,"remaining_time":0.6186131958},
{"learn":[2591406.002],"iteration":844,"passed_time":3.350666702,"remaining_time":0.6146193358},
{"learn":[2590804.324],"iteration":845,"passed_time":3.355077204,"remaining_time":0.6107350939},
{"learn":[2590182.374],"iteration":846,"passed_time":3.358973544,"remaining_time":0.6067567323},
{"learn":[2589725.535],"iteration":847,"passed_time":3.362983448,"remaining_time":0.6027989198},
{"learn":[2589229.298],"iteration":848,"passed_time":3.36650501,"remaining_time":0.5987541302},
{"learn":[2588763.95],"iteration":849,"passed_time":3.370576736,"remaining_time":0.5948076593},
{"learn":[2588556.468],"iteration":850,"passed_time":3.374253415,"remaining_time":0.5907917261},
{"learn":[2588124.978],"iteration":851,"passed_time":3.378449175,"remaining_time":0.5868667582},
{"learn":[2587630.17],"iteration":852,"passed_time":3.382285528,"remaining_time":0.5828792176},
{"learn":[2587087.798],"iteration":853,"passed_time":3.38608616,"remaining_time":0.5788859243},
{"learn":[2586505.332],"iteration":854,"passed_time":3.390523599,"remaining_time":0.5750010782},
{"learn":[2586186.392],"iteration":855,"passed_time":3.395213559,"remaining_time":0.5711574211},
{"learn":[2585479.966],"iteration":856,"passed_time":3.399346525,"remaining_time":0.5672188483},
{"learn":[2585211.709],"iteration":857,"passed_time":3.403017639,"remaining_time":0.5632033855},
{"learn":[2584769.103],"iteration":858,"passed_time":3.406611169,"remaining_time":0.5591759893},
{"learn":[2584361.384],"iteration":859,"passed_time":3.410787811,"remaining_time":0.5552445273},
{"learn":[2583780.133],"iteration":860,"passed_time":3.414854723,"remaining_time":0.551294781},
{"learn":[2583274.331],"iteration":861,"passed_time":3.420142611,"remaining_time":0.5475402324},
{"learn":[2582635.349],"iteration":862,"passed_time":3.423848587,"remaining_time":0.5435310039},
{"learn":[2581906.362],"iteration":863,"passed_time":3.427727974,"remaining_time":0.5395497738},
{"learn":[2581444.208],"iteration":864,"passed_time":3.432243173,"remaining_time":0.5356680097},
{"learn":[2580959.846],"iteration":865,"passed_time":3.436135859,"remaining_time":0.5316884586},
{"learn":[2580526.404],"iteration":866,"passed_time":3.440162367,"remaining_time":0.5277296365},
{"learn":[2579873.85],"iteration":867,"passed_time":3.444112943,"remaining_time":0.5237591111},
{"learn":[2579203.404],"iteration":868,"passed_time":3.448125753,"remaining_time":0.5197980134},
{"learn":[2578534.311],"iteration":869,"passed_time":3.452135767,"remaining_time":0.515836379},
{"learn":[2577691.824],"iteration":870,"passed_time":3.456053317,"remaining_time":0.511860939},
{"learn":[2576987.206],"iteration":871,"passed_time":3.460070697,"remaining_time":0.5079002858},
{"learn":[2576436.124],"iteration":872,"passed_time":3.464219915,"remaining_time":0.5039586819},
{"learn":[2575923.248],"iteration":873,"passed_time":3.46963242,"remaining_time":0.5001987241},
{"learn":[2575418.315],"iteration":874,"passed_time":3.473665797,"remaining_time":0.4962379709},
{"learn":[2574861.622],"iteration":875,"passed_time":3.477772334,"remaining_time":0.492287408},
{"learn":[2574354.114],"iteration":876,"passed_time":3.481855048,"remaining_time":0.4883331481},
{"learn":[2573941.671],"iteration":877,"passed_time":3.485699948,"remaining_time":0.4843455509},
{"learn":[2573570.774],"iteration":878,"passed_time":3.489481582,"remaining_time":0.4803495693},
{"learn":[2573277.515],"iteration":879,"passed_time":3.492852763,"remaining_time":0.4762981041},
{"learn":[2572671.537],"iteration":880,"passed_time":3.496840738,"remaining_time":0.4723314958},
{"learn":[2572146.023],"iteration":881,"passed_time":3.501080349,"remaining_time":0.4683985047},
{"learn":[2571766.712],"iteration":882,"passed_time":3.505192325,"remaining_time":0.4644479072},
{"learn":[2571331.724],"iteration":883,"passed_time":3.509054379,"remaining_time":0.4604641493},
{"learn":[2571041.555],"iteration":884,"passed_time":3.512816605,"remaining_time":0.4564676945},
{"learn":[2570666.78],"iteration":885,"passed_time":3.517065646,"remaining_time":0.4525344059},
{"learn":[2570238.605],"iteration":886,"passed_time":3.521047703,"remaining_time":0.4485663928},
{"learn":[2569600.865],"iteration":887,"passed_time":3.525264423,"remaining_time":0.4446279452},
{"learn":[2569246.312],"iteration":888,"passed_time":3.529252434,"remaining_time":0.4406603151},
{"learn":[2568842.93],"iteration":889,"passed_time":3.533029777,"remaining_time":0.4366666016},
{"learn":[2567869.762],"iteration":890,"passed_time":3.536950745,"remaining_time":0.4326909441},
{"learn":[2567341.794],"iteration":891,"passed_time":3.540703744,"remaining_time":0.4286950722},
{"learn":[2566712.187],"iteration":892,"passed_time":3.54478404,"remaining_time":0.4247389611},
{"learn":[2566292.164],"iteration":893,"passed_time":3.548616467,"remaining_time":0.4207531829},
{"learn":[2566196.727],"iteration":894,"passed_time":3.5523947,"remaining_time":0.4167613894},
{"learn":[2565569.405],"iteration":895,"passed_time":3.556764767,"remaining_time":0.4128387676},
{"learn":[2565082.394],"iteration":896,"passed_time":3.560756573,"remaining_time":0.4088717135},
{"learn":[2564684.751],"iteration":897,"passed_time":3.56459492,"remaining_time":0.4048871736},
{"learn":[2564314.673],"iteration":898,"passed_time":3.568094891,"remaining_time":0.4008649433},
{"learn":[2563825.617],"iteration":899,"passed_time":3.571617412,"remaining_time":0.3968463791},
{"learn":[2563303.241],"iteration":900,"passed_time":3.575142292,"remaining_time":0.3928291752},
{"learn":[2562673.532],"iteration":901,"passed_time":3.579063294,"remaining_time":0.3888561006},
{"learn":[2561963.935],"iteration":902,"passed_time":3.582884925,"remaining_time":0.384872467},
{"learn":[2561752.351],"iteration":903,"passed_time":3.586438133,"remaining_time":0.3808606867},
{"learn":[2561185.102],"iteration":904,"passed_time":3.591047536,"remaining_time":0.3769607911},
{"learn":[2560950.818],"iteration":905,"passed_time":3.594934588,"remaining_time":0.3729843833},
{"learn":[2560566.029],"iteration":906,"passed_time":3.598871004,"remaining_time":0.3690132342},
{"learn":[2560108.924],"iteration":907,"passed_time":3.602431723,"remaining_time":0.3650040952},
{"learn":[2559615.324],"iteration":908,"passed_time":3.60647079,"remaining_time":0.3610438305},
{"learn":[2559067.493],"iteration":909,"passed_time":3.610762591,"remaining_time":0.3571083881},
{"learn":[2558378.618],"iteration":910,"passed_time":3.614706665,"remaining_time":0.3531381923},
{"learn":[2557875.501],"iteration":911,"passed_time":3.619656198,"remaining_time":0.3492650717},
{"learn":[2557255.129],"iteration":912,"passed_time":3.623506288,"remaining_time":0.345284827},
{"learn":[2556379.303],"iteration":913,"passed_time":3.627572899,"remaining_time":0.34132524},
{"learn":[2555227.383],"iteration":914,"passed_time":3.631884664,"remaining_time":0.3373881928},
{"learn":[2554969.5],"iteration":915,"passed_time":3.635677869,"remaining_time":0.333402774},
{"learn":[2554359.566],"iteration":916,"passed_time":3.639692587,"remaining_time":0.3294378241},
{"learn":[2553832.677],"iteration":917,"passed_time":3.64382256,"remaining_time":0.3254830609},
{"learn":[2553366.315],"iteration":918,"passed_time":3.647787187,"remaining_time":0.3215133429},
{"learn":[2552864.992],"iteration":919,"passed_time":3.651622188,"remaining_time":0.3175323642},
{"learn":[2552340.978],"iteration":920,"passed_time":3.655716985,"remaining_time":0.3135739868},
{"learn":[2551903.277],"iteration":921,"passed_time":3.659734056,"remaining_time":0.3096087379},
{"learn":[2551504.109],"iteration":922,"passed_time":3.663581819,"remaining_time":0.3056292525},
{"learn":[2551104.883],"iteration":923,"passed_time":3.667170596,"remaining_time":0.3016287503},
{"learn":[2550508.664],"iteration":924,"passed_time":3.672526699,"remaining_time":0.2977724351},
{"learn":[2550136.58],"iteration":925,"passed_time":3.676312711,"remaining_time":0.2937874088},
{"learn":[2549616.628],"iteration":926,"passed_time":3.680408441,"remaining_time":0.2898272019},
{"learn":[2549219.9],"iteration":927,"passed_time":3.684059589,"remaining_time":0.2858322095},
{"learn":[2548907.14],"iteration":928,"passed_time":3.687824837,"remaining_time":0.2818466775},
{"learn":[2547692.88],"iteration":929,"passed_time":3.691887955,"remaining_time":0.2778840396},
{"learn":[2547208.898],"iteration":930,"passed_time":3.695513141,"remaining_time":0.273888729},
{"learn":[2546619.545],"iteration":931,"passed_time":3.699384967,"remaining_time":0.2699122079},
{"learn":[2545823.613],"iteration":932,"passed_time":3.704400143,"remaining_time":0.2660180167},
{"learn":[2545410.289],"iteration":933,"passed_time":3.708142025,"remaining_time":0.2620314493},
{"learn":[2544972.465],"iteration":934,"passed_time":3.711859248,"remaining_time":0.258043691},
{"learn":[2544802.756],"iteration":935,"passed_time":3.715404495,"remaining_time":0.2540447518},
{"learn":[2544680.135],"iteration":936,"passed_time":3.718881073,"remaining_time":0.2500421639},
{"learn":[2544295.71],"iteration":937,"passed_time":3.722642865,"remaining_time":0.2460595497},
{"learn":[2543811.249],"iteration":938,"passed_time":3.726775715,"remaining_time":0.2421015108},
{"learn":[2543194.519],"iteration":939,"passed_time":3.730767312,"remaining_time":0.2381340838},
{"learn":[2542659.718],"iteration":940,"passed_time":3.734523634,"remaining_time":0.2341518538},
{"learn":[2542319.899],"iteration":941,"passed_time":3.738070056,"remaining_time":0.2301571797},
{"learn":[2542206.393],"iteration":942,"passed_time":3.7415543,"remaining_time":0.2261596979},
{"learn":[2541730.094],"iteration":943,"passed_time":3.745635069,"remaining_time":0.2221986905},
{"learn":[2541398.722],"iteration":944,"passed_time":3.749541636,"remaining_time":0.218227291},
{"learn":[2540756.58],"iteration":945,"passed_time":3.753662638,"remaining_time":0.214268269},
{"learn":[2540349.028],"iteration":946,"passed_time":3.757540725,"remaining_time":0.2102953099},
{"learn":[2539779.177],"iteration":947,"passed_time":3.761233082,"remaining_time":0.2063123631},
{"learn":[2539669.951],"iteration":948,"passed_time":3.764425311,"remaining_time":0.2023031516},
{"learn":[2539082.45],"iteration":949,"passed_time":3.768204799,"remaining_time":0.1983265684},
{"learn":[2538481.202],"iteration":950,"passed_time":3.772142808,"remaining_time":0.1943585674},
{"learn":[2538097.699],"iteration":951,"passed_time":3.776716214,"remaining_time":0.1904226662},
{"learn":[2537618.704],"iteration":952,"passed_time":3.780564924,"remaining_time":0.1864496867},
{"learn":[2536888.517],"iteration":953,"passed_time":3.7843099,"remaining_time":0.1824719658},
{"learn":[2536583.145],"iteration":954,"passed_time":3.788100395,"remaining_time":0.1784968772},
{"learn":[2536054.621],"iteration":955,"passed_time":3.792158637,"remaining_time":0.1745344979},
{"learn":[2535727.5],"iteration":956,"passed_time":3.795898909,"remaining_time":0.1705576312},
{"learn":[2535130.786],"iteration":957,"passed_time":3.80008709,"remaining_time":0.1666008954},
{"learn":[2534633.738],"iteration":958,"passed_time":3.80383648,"remaining_time":0.1626249173},
{"learn":[2534325.956],"iteration":959,"passed_time":3.807413403,"remaining_time":0.1586422251},
{"learn":[2533984.8],"iteration":960,"passed_time":3.81108037,"remaining_time":0.1546640316},
{"learn":[2533354.182],"iteration":961,"passed_time":3.814816825,"remaining_time":0.1506892301},
{"learn":[2532679.953],"iteration":962,"passed_time":3.819572701,"remaining_time":0.1467540913},
{"learn":[2532019.259],"iteration":963,"passed_time":3.823474829,"remaining_time":0.1427853671},
{"learn":[2531469.804],"iteration":964,"passed_time":3.827125536,"remaining_time":0.1388076619},
{"learn":[2531132.458],"iteration":965,"passed_time":3.831249257,"remaining_time":0.1348472824},
{"learn":[2530587.261],"iteration":966,"passed_time":3.835722828,"remaining_time":0.1308985039},
{"learn":[2529977.212],"iteration":967,"passed_time":3.839332069,"remaining_time":0.1269200684},
{"learn":[2529466.396],"iteration":968,"passed_time":3.843008271,"remaining_time":0.122944537},
{"learn":[2529166.297],"iteration":969,"passed_time":3.846873517,"remaining_time":0.1189754696},
{"learn":[2528506.186],"iteration":970,"passed_time":3.850693664,"remaining_time":0.1150052691},
{"learn":[2527976.057],"iteration":971,"passed_time":3.854330112,"remaining_time":0.1110300855},
{"learn":[2527261.567],"iteration":972,"passed_time":3.858320176,"remaining_time":0.1070654108},
{"learn":[2526790.381],"iteration":973,"passed_time":3.862364028,"remaining_time":0.1031021198},
{"learn":[2526077.929],"iteration":974,"passed_time":3.867022676,"remaining_time":0.09915442758},
{"learn":[2525613.559],"iteration":975,"passed_time":3.871058053,"remaining_time":0.09518995213},
{"learn":[2525043.158],"iteration":976,"passed_time":3.875132028,"remaining_time":0.09122624017},
{"learn":[2524456.444],"iteration":977,"passed_time":3.879266903,"remaining_time":0.08726367265},
{"learn":[2524326.281],"iteration":978,"passed_time":3.882677533,"remaining_time":0.08328521776},
{"learn":[2523740.233],"iteration":979,"passed_time":3.886727866,"remaining_time":0.07932097685},
{"learn":[2523552.073],"iteration":980,"passed_time":3.890263726,"remaining_time":0.07534659612},
{"learn":[2523166.61],"iteration":981,"passed_time":3.893950204,"remaining_time":0.07137586932},
{"learn":[2522702.612],"iteration":982,"passed_time":3.897658596,"remaining_time":0.06740609983},
{"learn":[2521962.805],"iteration":983,"passed_time":3.901525707,"remaining_time":0.06343944239},
{"learn":[2521486.104],"iteration":984,"passed_time":3.90521396,"remaining_time":0.05947026335},
{"learn":[2520920.017],"iteration":985,"passed_time":3.909287467,"remaining_time":0.05550712427},
{"learn":[2520380.12],"iteration":986,"passed_time":3.913016093,"remaining_time":0.05153921906},
{"learn":[2519958.28],"iteration":987,"passed_time":3.916759936,"remaining_time":0.04757198303},
{"learn":[2519511.459],"iteration":988,"passed_time":3.920431382,"remaining_time":0.04360439353},
{"learn":[2518774.626],"iteration":989,"passed_time":3.924558744,"remaining_time":0.03964200751},
{"learn":[2518341.085],"iteration":990,"passed_time":3.928556986,"remaining_time":0.03567811592},
{"learn":[2517874.097],"iteration":991,"passed_time":3.932615419,"remaining_time":0.03171464048},
{"learn":[2517426.08],"iteration":992,"passed_time":3.936413485,"remaining_time":0.02774913836},
{"learn":[2517118.848],"iteration":993,"passed_time":3.940264188,"remaining_time":0.02378429088},
{"learn":[2516679.056],"iteration":994,"passed_time":3.944015258,"remaining_time":0.01981917215},
{"learn":[2516419.618],"iteration":995,"passed_time":3.947857132,"remaining_time":0.01585484792},
{"learn":[2516091.808],"iteration":996,"passed_time":3.951494364,"remaining_time":0.01189015355},
{"learn":[2515706.121],"iteration":997,"passed_time":3.955145161,"remaining_time":0.007926142607},
{"learn":[2515211.217],"iteration":998,"passed_time":3.959317104,"remaining_time":0.003963280384},
{"learn":[2515191.743],"iteration":999,"passed_time":3.962621593,"remaining_time":0}
]}